{"root":0,"children":[{"move":3096,"grade":0,"children":[{"move":11952,"grade":0,"children":[{"grade":100,"solution":1552},{"grade":103,"solution":1643},{"move":22,"grade":203,"children":[{"grade":101,"solution":1729},{"grade":201,"solution":987},{"grade":1110,"solution":1405},{"grade":2050,"solution":2201}]},{"grade":204,"move":1570,"children":[{"grade":5100,"solution":1570},{"grade":1215,"solution":2189}]},{"grade":205,"solution":645},{"grade":304,"solution":699},{"grade":305,"move":826,"children":[{"grade":5100,"solution":826},{"grade":4090,"solution":1769}]},{"grade":307,"move":571,"children":[{"grade":5100,"solution":571},{"grade":1410,"solution":1467}]},{"grade":308,"solution":932},{"grade":407,"solution":1596},{"grade":409,"solution":550},{"grade":1113,"solution":1203},{"grade":1123,"move":508,"children":[{"grade":5100,"solution":508},{"grade":4164,"solution":1494}]},{"grade":1243,"solution":817},{"grade":2020,"solution":1551},{"grade":2030,"solution":3},{"grade":2133,"move":778,"children":[{"grade":5100,"solution":778},{"grade":4060,"solution":1958}]}]},{"move":898,"grade":100,"children":[{"grade":203,"solution":1812},{"grade":204,"solution":281},{"grade":303,"solution":1854},{"grade":306,"solution":430},{"grade":1112,"solution":575},{"grade":2152,"solution":688},{"grade":2161,"solution":1080},{"grade":3070,"move":1358,"children":[{"grade":5100,"solution":1358},{"grade":4173,"solution":1518}]},{"grade":3170,"solution":2154},{"grade":4070,"solution":1211},{"grade":5100,"solution":898}]},{"move":9076,"grade":101,"children":[{"move":116,"grade":0,"children":[{"grade":2132,"solution":634},{"grade":2134,"solution":1640},{"grade":2236,"solution":1067},{"grade":4090,"solution":773}]},{"grade":100,"move":1540,"children":[{"grade":5100,"solution":1540},{"grade":1309,"solution":2239}]},{"grade":101,"solution":1929},{"grade":103,"solution":493},{"grade":203,"solution":39},{"grade":303,"solution":65},{"grade":305,"solution":414},{"grade":407,"solution":810},{"grade":1010,"solution":413},{"grade":1040,"solution":769},{"grade":1110,"solution":1524},{"grade":1113,"solution":1179},{"grade":1130,"solution":351},{"grade":1213,"solution":473},{"grade":1215,"solution":1152},{"grade":1221,"solution":1265},{"grade":1333,"solution":1846},{"grade":2133,"move":420,"children":[{"grade":5100,"solution":420},{"grade":4060,"solution":2251}]},{"grade":2233,"solution":1115},{"grade":3070,"solution":1840},{"grade":3080,"solution":520}]},{"move":202,"grade":102,"children":[{"grade":304,"solution":678},{"grade":309,"solution":88},{"grade":406,"solution":1646},{"grade":409,"solution":1714},{"grade":1143,"solution":1287},{"grade":2050,"solution":387},{"grade":2070,"solution":2032},{"grade":2154,"solution":2294},{"grade":2163,"move":1118,"children":[{"grade":5100,"solution":1118},{"grade":4200,"solution":1423}]},{"grade":2254,"solution":740},{"grade":3090,"solution":1464},{"grade":4060,"solution":1944},{"grade":5100,"solution":202}]},{"move":1530,"grade":103,"children":[{"grade":202,"move":465,"children":[{"grade":5100,"solution":465},{"grade":1104,"solution":1995}]},{"grade":303,"solution":1373},{"grade":1020,"solution":793},{"grade":1102,"solution":1363},{"grade":1120,"solution":460},{"grade":1224,"solution":1513},{"grade":1307,"solution":415},{"grade":2020,"solution":2124},{"grade":2124,"solution":1693},{"grade":2150,"solution":121},{"grade":2160,"solution":125},{"grade":2161,"move":1374,"children":[{"grade":5100,"solution":1374},{"grade":3173,"solution":2036}]},{"grade":2261,"solution":1240},{"grade":3050,"solution":1294},{"grade":3060,"solution":1010},{"grade":3191,"solution":902},{"grade":4090,"solution":262},{"grade":5100,"solution":1530}]},{"grade":104,"solution":115},{"move":9076,"grade":201,"children":[{"grade":0,"solution":2179},{"grade":100,"solution":2247},{"grade":201,"solution":972},{"grade":203,"solution":1007},{"grade":303,"solution":287},{"move":68,"grade":1020,"children":[{"grade":1020,"solution":1992},{"grade":1121,"solution":577},{"grade":2060,"solution":282}]},{"grade":1112,"solution":1150},{"grade":1113,"solution":263},{"grade":1120,"solution":857},{"grade":1121,"solution":222},{"grade":1123,"solution":2252},{"grade":2060,"solution":49},{"grade":2070,"solution":1424}]},{"move":22,"grade":202,"children":[{"grade":0,"solution":1237},{"grade":101,"solution":1922},{"grade":1040,"solution":1740}]},{"move":810,"grade":203,"children":[{"grade":0,"move":1498,"children":[{"grade":5100,"solution":1498},{"grade":2154,"solution":1764}]},{"grade":101,"move":36,"children":[{"grade":5100,"solution":36},{"grade":4080,"solution":1592}]},{"grade":102,"move":286,"children":[{"grade":5100,"solution":286},{"grade":2217,"solution":1491}]},{"grade":202,"move":461,"children":[{"grade":5100,"solution":461},{"grade":2235,"solution":921}]},{"grade":203,"solution":1040},{"grade":307,"solution":1659},{"grade":1000,"solution":896},{"grade":1010,"solution":578},{"grade":1020,"solution":2038},{"grade":1101,"solution":52},{"grade":1114,"solution":897},{"grade":1123,"solution":89},{"grade":1124,"solution":31},{"grade":1203,"solution":99},{"grade":1205,"solution":498},{"grade":2060,"solution":276},{"grade":2070,"solution":107},{"grade":2160,"solution":490},{"grade":3030,"solution":511},{"grade":3070,"solution":1544}]},{"move":414,"grade":204,"children":[{"grade":202,"solution":2149},{"grade":203,"solution":1962},{"grade":206,"solution":717},{"move":2,"grade":306,"children":[{"grade":0,"solution":77},{"grade":2134,"solution":1346},{"grade":2216,"solution":1292}]},{"grade":307,"solution":1350},{"grade":1020,"solution":661},{"grade":1120,"solution":280},{"grade":1123,"solution":1977},{"grade":1124,"solution":2230},{"grade":1225,"solution":2135},{"grade":1227,"solution":227},{"grade":2060,"solution":1251},{"grade":2160,"solution":914},{"grade":2161,"solution":576},{"grade":2264,"solution":1869},{"grade":3090,"move":285,"children":[{"grade":5100,"solution":285},{"grade":4090,"solution":1546}]}]},{"move":11146,"grade":205,"children":[{"grade":0,"solution":1509},{"grade":101,"move":1209,"children":[{"grade":5100,"solution":1209},{"grade":2112,"solution":1868}]},{"grade":202,"solution":1223},{"grade":204,"solution":540},{"grade":205,"solution":53},{"grade":1010,"move":37,"children":[{"grade":5100,"solution":37},{"grade":2134,"solution":1243}]},{"grade":1112,"solution":777},{"grade":1113,"solution":871},{"grade":1121,"move":732,"children":[{"grade":5100,"solution":732},{"grade":3154,"solution":1215}]},{"grade":1123,"solution":467},{"grade":1141,"move":630,"children":[{"grade":5100,"solution":630},{"grade":4100,"solution":2290}]},{"grade":1221,"move":68,"children":[{"grade":5100,"solution":68},{"grade":4060,"solution":563}]},{"grade":1224,"solution":1449},{"grade":1244,"move":655,"children":[{"grade":5100,"solution":655},{"grade":4191,"solution":1630}]},{"move":290,"grade":2050,"children":[{"grade":2040,"solution":533},{"grade":2141,"solution":1427},{"grade":2170,"solution":1160},{"grade":3070,"solution":1039}]},{"grade":2133,"solution":168},{"grade":2150,"solution":1091},{"grade":2153,"solution":619},{"grade":2171,"solution":1086},{"grade":2253,"solution":268},{"grade":3080,"solution":2134}]},{"grade":206,"solution":1816},{"grade":207,"solution":668},{"grade":303,"solution":219},{"move":414,"grade":304,"children":[{"grade":102,"solution":611},{"grade":203,"solution":340},{"grade":206,"solution":1808},{"grade":309,"solution":450},{"grade":1020,"solution":788},{"grade":1120,"solution":1833},{"grade":1124,"solution":927},{"grade":2060,"solution":1472},{"grade":3090,"solution":1904}]},{"grade":305,"move":774,"children":[{"grade":5100,"solution":774},{"grade":3291,"solution":1889}]},{"move":10772,"grade":306,"children":[{"grade":102,"solution":806},{"grade":202,"solution":1565},{"grade":203,"move":656,"children":[{"grade":5100,"solution":656},{"grade":4060,"solution":758}]},{"grade":205,"solution":12},{"grade":206,"solution":535},{"grade":303,"solution":1406},{"grade":305,"solution":1883},{"grade":1020,"solution":411},{"grade":1121,"solution":1561},{"grade":1124,"solution":606},{"grade":2060,"solution":1310},{"grade":2160,"solution":1212}]},{"grade":307,"solution":739},{"grade":308,"solution":1453},{"grade":406,"solution":1398},{"grade":407,"solution":1372},{"grade":408,"solution":1760},{"grade":510,"solution":1504},{"move":414,"grade":1010,"children":[{"grade":2020,"solution":456},{"grade":2060,"solution":847},{"grade":2160,"move":1600,"children":[{"grade":5100,"solution":1600},{"grade":4100,"solution":2025}]},{"grade":2163,"solution":1343},{"grade":3060,"solution":1798},{"grade":3090,"solution":913},{"grade":4090,"solution":2232}]},{"move":1160,"grade":1020,"children":[{"grade":101,"solution":138},{"grade":1010,"solution":2119},{"grade":1110,"solution":2098},{"grade":1141,"solution":1352},{"grade":2050,"solution":2244}]},{"move":11562,"grade":1030,"children":[{"grade":102,"solution":1534},{"grade":206,"solution":888},{"grade":303,"solution":1501},{"grade":306,"solution":2211},{"grade":307,"move":314,"children":[{"grade":5100,"solution":314},{"grade":1233,"solution":327}]},{"grade":309,"solution":1522},{"grade":409,"solution":354},{"grade":1020,"solution":1595},{"grade":1121,"solution":60},{"grade":1142,"solution":2243},{"grade":1242,"solution":2097},{"grade":1243,"solution":2096},{"grade":1307,"solution":2194},{"grade":2163,"solution":1617}]},{"grade":1040,"move":816,"children":[{"grade":5100,"solution":816},{"grade":3070,"solution":1046}]},{"grade":1101,"move":313,"children":[{"grade":5100,"solution":313},{"grade":3030,"solution":2172}]},{"move":2,"grade":1103,"children":[{"grade":0,"solution":975},{"grade":100,"solution":1474},{"grade":1243,"solution":613}]},{"grade":1110,"move":1109,"children":[{"grade":5100,"solution":1109},{"grade":2255,"solution":1387}]},{"move":24,"grade":1112,"children":[{"grade":2130,"solution":356},{"grade":3170,"solution":1867},{"grade":4070,"solution":1638},{"grade":5100,"solution":24}]},{"grade":1113,"solution":1505},{"move":354,"grade":1121,"children":[{"grade":0,"move":534,"children":[{"grade":5100,"solution":534},{"grade":4060,"solution":878}]},{"grade":100,"solution":1437},{"grade":102,"solution":977},{"grade":104,"solution":772},{"grade":1040,"solution":892}]},{"grade":1123,"move":1681,"children":[{"grade":5100,"solution":1681},{"grade":3151,"solution":2238}]},{"move":272,"grade":1130,"children":[{"grade":100,"move":443,"children":[{"grade":5100,"solution":443},{"grade":2236,"solution":1957}]},{"grade":201,"solution":737},{"grade":1000,"solution":1155},{"grade":1102,"solution":1139},{"grade":1104,"solution":1219},{"grade":1110,"solution":2075},{"grade":1205,"solution":1394},{"grade":2040,"solution":1735}]},{"grade":1131,"move":1233,"children":[{"grade":5100,"solution":1233},{"grade":2235,"solution":1589}]},{"move":8,"grade":1132,"children":[{"grade":100,"solution":596},{"grade":1000,"solution":1471},{"grade":2020,"solution":1005}]},{"grade":1134,"solution":1614},{"grade":1140,"solution":1206},{"move":314,"grade":1141,"children":[{"grade":203,"solution":197},{"grade":1000,"move":54,"children":[{"grade":5100,"solution":54},{"grade":4182,"solution":405}]},{"grade":1010,"solution":1756},{"grade":1104,"solution":130},{"grade":2010,"solution":1909},{"grade":2020,"solution":1727}]},{"grade":1142,"move":5,"children":[{"grade":5100,"solution":5},{"grade":3090,"solution":416}]},{"grade":1143,"move":1818,"children":[{"grade":5100,"solution":1818},{"grade":2170,"solution":1832}]},{"grade":1203,"solution":765},{"move":152,"grade":1204,"children":[{"grade":103,"solution":891},{"grade":1030,"solution":1926},{"grade":1131,"move":868,"children":[{"grade":5100,"solution":868},{"grade":4060,"solution":1754}]},{"grade":1132,"solution":129},{"grade":1134,"solution":441}]},{"grade":1205,"solution":2023},{"move":106,"grade":1213,"children":[{"grade":102,"solution":1345},{"grade":202,"solution":2063},{"grade":205,"solution":494}]},{"grade":1215,"solution":1507},{"grade":1224,"solution":165},{"grade":1232,"solution":2200},{"grade":1241,"move":1153,"children":[{"grade":5100,"solution":1153},{"grade":2273,"solution":1695}]},{"grade":1242,"solution":1202},{"grade":1244,"solution":463},{"move":12,"grade":1245,"children":[{"grade":201,"solution":829},{"grade":1110,"solution":2190},{"grade":1212,"solution":74}]},{"grade":1306,"solution":1675},{"grade":1319,"solution":1477},{"grade":1343,"solution":835},{"grade":1344,"solution":2061},{"grade":1345,"solution":1602},{"move":4,"grade":1346,"children":[{"grade":203,"solution":659},{"grade":1000,"solution":735},{"grade":2010,"solution":250}]},{"grade":2010,"move":1048,"children":[{"grade":5100,"solution":1048},{"grade":4070,"solution":1609}]},{"grade":2030,"move":1142,"children":[{"grade":5100,"solution":1142},{"grade":4080,"solution":1465}]},{"grade":2040,"move":279,"children":[{"grade":5100,"solution":279},{"grade":3180,"solution":1392}]},{"move":60,"grade":2050,"children":[{"grade":0,"solution":1001},{"grade":104,"solution":907},{"grade":1132,"solution":595},{"grade":1233,"solution":334},{"grade":1236,"solution":1480},{"grade":2132,"solution":1117}]},{"grade":2060,"move":1218,"children":[{"grade":5100,"solution":1218},{"grade":4191,"solution":1994}]},{"grade":2070,"move":792,"children":[{"grade":5100,"solution":792},{"grade":2171,"solution":1403}]},{"grade":2140,"solution":693},{"grade":2151,"solution":2273},{"grade":2152,"move":865,"children":[{"grade":5100,"solution":865},{"grade":4100,"solution":1625}]},{"move":178,"grade":2172,"children":[{"grade":1000,"solution":2105},{"grade":1104,"solution":1307},{"grade":2020,"solution":850}]},{"grade":2243,"solution":367},{"grade":3030,"solution":1943},{"grade":3040,"solution":1639},{"grade":3090,"move":58,"children":[{"grade":5100,"solution":58},{"grade":4100,"solution":2005}]},{"grade":3142,"solution":2129},{"grade":4060,"move":1763,"children":[{"grade":5100,"solution":1763},{"grade":4060,"solution":2215}]},{"grade":4100,"solution":1408}]},{"move":810,"grade":100,"children":[{"move":1470,"grade":0,"children":[{"grade":205,"solution":1071},{"grade":305,"solution":421},{"grade":306,"move":1328,"children":[{"grade":5100,"solution":1328},{"grade":4060,"solution":1487}]},{"grade":1102,"solution":861},{"grade":1120,"solution":1858},{"grade":1132,"move":1270,"children":[{"grade":5100,"solution":1270},{"grade":4080,"solution":1886}]},{"grade":1203,"solution":1145},{"grade":1205,"solution":996},{"grade":1236,"solution":274},{"grade":2050,"solution":811},{"grade":2132,"solution":458},{"move":524,"grade":3050,"children":[{"grade":201,"solution":1401},{"grade":1110,"solution":191},{"grade":1212,"solution":1949},{"grade":1213,"solution":1945}]},{"grade":3090,"solution":751},{"grade":3142,"solution":2015},{"grade":3151,"solution":617},{"grade":5100,"solution":1470}]},{"move":562,"grade":100,"children":[{"grade":304,"solution":539},{"grade":406,"solution":1853},{"grade":1204,"solution":1198},{"grade":1231,"solution":394},{"grade":1315,"solution":1755},{"grade":2113,"solution":529},{"grade":2140,"solution":1436}]},{"move":1858,"grade":101,"children":[{"grade":203,"solution":1083},{"grade":306,"solution":1458},{"grade":1112,"solution":1068},{"grade":1215,"solution":205},{"grade":1224,"solution":1397},{"grade":2133,"solution":951},{"grade":2233,"solution":2123},{"grade":2264,"solution":997}]},{"move":1470,"grade":102,"children":[{"grade":205,"solution":524},{"grade":303,"solution":388},{"grade":306,"solution":2266},{"grade":1121,"solution":132},{"grade":1124,"solution":736},{"grade":1203,"solution":116},{"grade":1227,"solution":2024},{"grade":2020,"move":1093,"children":[{"grade":5100,"solution":1093},{"grade":4060,"solution":2143}]},{"grade":2112,"solution":1342},{"grade":2124,"solution":785},{"grade":2133,"solution":1319},{"grade":2154,"solution":151},{"grade":3030,"solution":1805}]},{"move":8,"grade":103,"children":[{"grade":0,"solution":223},{"grade":100,"solution":647},{"grade":104,"solution":1306},{"grade":1000,"solution":2164}]},{"move":10,"grade":104,"children":[{"grade":103,"solution":1792},{"grade":1030,"solution":801},{"grade":1207,"solution":22}]},{"move":32,"grade":201,"children":[{"grade":0,"solution":1355},{"grade":102,"solution":1300},{"grade":103,"solution":1952},{"grade":104,"solution":2148}]},{"move":1926,"grade":202,"children":[{"grade":103,"solution":1841},{"grade":204,"solution":377},{"grade":207,"solution":1627},{"grade":306,"solution":2100},{"grade":1030,"move":55,"children":[{"grade":5100,"solution":55},{"grade":4100,"solution":1301}]},{"grade":1130,"solution":1872},{"grade":1131,"solution":2208},{"grade":2070,"solution":1166}]},{"grade":203,"move":90,"children":[{"grade":5100,"solution":90},{"grade":2255,"solution":257}]},{"move":30,"grade":204,"children":[{"grade":1103,"solution":1482},{"grade":1207,"solution":255},{"grade":2143,"solution":1137},{"grade":3070,"solution":1742},{"grade":4080,"solution":1531}]},{"move":16,"grade":205,"children":[{"grade":0,"solution":1635},{"grade":103,"solution":1722},{"grade":204,"solution":1974},{"grade":1131,"solution":716}]},{"move":4,"grade":206,"children":[{"grade":100,"solution":2195},{"grade":1000,"solution":1996},{"grade":1103,"solution":1824}]},{"grade":207,"solution":2229},{"grade":303,"move":1419,"children":[{"grade":5100,"solution":1419},{"grade":410,"solution":2231}]},{"grade":304,"solution":1972},{"grade":305,"move":198,"children":[{"grade":5100,"solution":198},{"grade":510,"solution":376}]},{"grade":306,"solution":2286},{"grade":307,"solution":881},{"grade":308,"move":482,"children":[{"grade":5100,"solution":482},{"grade":510,"solution":684}]},{"grade":1000,"move":1982,"children":[{"grade":5100,"solution":1982},{"grade":1306,"solution":2002}]},{"grade":1010,"move":1669,"children":[{"grade":5100,"solution":1669},{"grade":3180,"solution":1692}]},{"move":1602,"grade":1020,"children":[{"grade":0,"solution":401},{"grade":101,"solution":673},{"grade":102,"solution":2132},{"grade":201,"solution":2137},{"grade":202,"move":131,"children":[{"grade":5100,"solution":131},{"grade":3255,"solution":1181}]},{"grade":203,"move":378,"children":[{"grade":5100,"solution":378},{"grade":4191,"solution":1320}]},{"grade":1000,"solution":106},{"grade":1040,"move":1495,"children":[{"grade":5100,"solution":1495},{"grade":4100,"solution":1732}]},{"grade":1141,"solution":2217},{"grade":1142,"solution":1801},{"grade":1212,"solution":1925},{"grade":2010,"solution":1135},{"grade":2040,"solution":1027}]},{"grade":1040,"move":9,"children":[{"grade":5100,"solution":9},{"grade":2263,"solution":1393}]},{"move":38,"grade":1101,"children":[{"grade":207,"solution":934},{"grade":307,"solution":139},{"grade":1134,"solution":2044}]},{"grade":1102,"move":215,"children":[{"grade":5100,"solution":215},{"grade":1308,"solution":1169}]},{"move":2,"grade":1104,"children":[{"grade":1216,"solution":568},{"grade":1225,"solution":681},{"grade":1316,"solution":408}]},{"grade":1110,"solution":2218},{"grade":1112,"solution":1924},{"grade":1114,"solution":196},{"move":394,"grade":1120,"children":[{"grade":203,"solution":194},{"grade":303,"solution":248},{"grade":306,"solution":249},{"grade":1215,"solution":159},{"grade":2112,"solution":353},{"grade":3152,"solution":2168}]},{"move":1602,"grade":1123,"children":[{"grade":0,"move":213,"children":[{"grade":5100,"solution":213},{"grade":3090,"solution":1836}]},{"grade":100,"solution":1234},{"grade":102,"solution":163},{"grade":103,"solution":1289},{"grade":206,"solution":1610},{"grade":1112,"solution":648}]},{"grade":1124,"solution":670},{"grade":1140,"solution":1291},{"grade":1141,"solution":1737},{"grade":1142,"solution":695},{"grade":1204,"solution":621},{"grade":1205,"move":1380,"children":[{"grade":5100,"solution":1380},{"grade":2215,"solution":2022}]},{"grade":1206,"solution":901},{"grade":1223,"move":288,"children":[{"grade":5100,"solution":288},{"grade":3191,"solution":1631}]},{"grade":1227,"solution":767},{"grade":1244,"solution":1228},{"grade":1316,"solution":1746},{"grade":2010,"solution":1},{"grade":2020,"solution":79},{"grade":2050,"move":80,"children":[{"grade":5100,"solution":80},{"grade":3070,"solution":1197}]},{"move":274,"grade":2060,"children":[{"grade":204,"solution":1566},{"grade":206,"solution":2125},{"grade":306,"solution":969},{"grade":308,"solution":2130},{"grade":408,"solution":780},{"grade":410,"solution":2245}]},{"grade":2070,"move":1539,"children":[{"grade":5100,"solution":1539},{"grade":2373,"solution":1689}]},{"grade":2124,"move":1907,"children":[{"grade":5100,"solution":1907},{"grade":3133,"solution":2174}]},{"grade":2133,"solution":1710},{"grade":2153,"solution":1481},{"move":340,"grade":2160,"children":[{"grade":103,"solution":944},{"grade":204,"solution":162},{"grade":207,"solution":979},{"grade":1103,"solution":320}]},{"grade":2171,"solution":1267},{"grade":3030,"solution":976},{"grade":3050,"solution":933},{"grade":3060,"move":1227,"children":[{"grade":5100,"solution":1227},{"grade":4070,"solution":1386}]},{"grade":3090,"solution":999},{"grade":3171,"solution":1588},{"grade":4090,"solution":797}]},{"move":522,"grade":101,"children":[{"move":8870,"grade":102,"children":[{"grade":204,"solution":152},{"grade":1030,"move":2019,"children":[{"grade":5100,"solution":2019},{"grade":3090,"solution":2131}]},{"grade":1130,"solution":347},{"grade":1132,"solution":2197},{"grade":1134,"solution":1381},{"grade":2030,"move":1253,"children":[{"grade":5100,"solution":1253},{"grade":2030,"solution":1733}]},{"grade":2050,"solution":2103},{"grade":2123,"solution":1311},{"grade":2134,"solution":2199},{"grade":3040,"move":552,"children":[{"grade":5100,"solution":552},{"grade":3246,"solution":1421}]},{"grade":3050,"move":525,"children":[{"grade":5100,"solution":525},{"grade":4060,"solution":632}]},{"grade":4060,"move":491,"children":[{"grade":5100,"solution":491},{"grade":4164,"solution":635}]},{"grade":4080,"solution":1998}]},{"move":6432,"grade":202,"children":[{"grade":100,"solution":208},{"grade":202,"solution":1399},{"grade":303,"solution":1156},{"grade":305,"solution":1283},{"grade":1102,"solution":124},{"grade":1120,"solution":1641},{"grade":1242,"solution":958},{"grade":2020,"solution":1911},{"grade":2142,"solution":1826}]},{"move":3284,"grade":203,"children":[{"grade":103,"solution":671},{"grade":204,"solution":372},{"grade":205,"solution":2282},{"grade":1030,"solution":464},{"grade":1103,"solution":729},{"grade":1123,"solution":1238},{"grade":1134,"solution":342},{"grade":1233,"solution":273},{"grade":2050,"move":519,"children":[{"grade":5100,"solution":519},{"grade":3090,"solution":1799}]},{"grade":2132,"solution":2034},{"grade":2143,"solution":1590}]},{"move":3576,"grade":205,"children":[{"grade":0,"solution":1216},{"grade":101,"solution":984},{"grade":104,"move":1691,"children":[{"grade":5100,"solution":1691},{"grade":2337,"solution":1975}]},{"grade":204,"solution":1157},{"move":248,"grade":205,"children":[{"grade":204,"move":123,"children":[{"grade":5100,"solution":123},{"grade":4060,"solution":2274}]},{"grade":307,"solution":1389},{"grade":1140,"solution":457}]},{"grade":207,"solution":722},{"grade":306,"solution":2225},{"move":1290,"grade":1000,"children":[{"grade":104,"solution":426},{"grade":204,"solution":986},{"grade":1040,"solution":839},{"grade":1140,"solution":1796}]},{"grade":1030,"solution":957},{"grade":1102,"solution":1455},{"grade":1104,"solution":1650},{"grade":1142,"solution":183},{"grade":2040,"solution":29},{"grade":2050,"solution":2223},{"grade":3050,"solution":946}]},{"move":2,"grade":206,"children":[{"grade":1225,"solution":786},{"grade":1316,"solution":126},{"grade":2216,"solution":1479}]},{"move":1116,"grade":303,"children":[{"grade":103,"solution":903},{"grade":1030,"move":429,"children":[{"grade":5100,"solution":429},{"grade":3144,"solution":876}]},{"grade":1103,"solution":1725},{"grade":1130,"solution":675},{"grade":1132,"solution":66},{"grade":1134,"solution":1587},{"grade":2050,"solution":83}]},{"move":124,"grade":305,"children":[{"grade":407,"solution":844},{"grade":409,"solution":1750},{"grade":1224,"solution":1210},{"grade":1345,"solution":803},{"grade":2124,"solution":1149}]},{"move":112,"grade":306,"children":[{"grade":207,"solution":515},{"grade":410,"solution":1887},{"grade":1140,"solution":311},{"grade":1241,"solution":1098},{"grade":2172,"solution":2092},{"grade":3090,"solution":231}]},{"grade":307,"move":658,"children":[{"grade":5100,"solution":658},{"grade":2142,"solution":1535}]},{"move":148,"grade":309,"children":[{"grade":1102,"move":256,"children":[{"grade":5100,"solution":256},{"grade":4060,"solution":1094}]},{"grade":1142,"solution":1795},{"grade":1203,"solution":315},{"grade":2142,"solution":2178},{"grade":3060,"solution":1299}]},{"grade":406,"move":75,"children":[{"grade":5100,"solution":75},{"grade":1324,"solution":556}]},{"grade":407,"solution":1414},{"grade":409,"solution":344},{"grade":1020,"solution":1813},{"move":816,"grade":1102,"children":[{"grade":0,"solution":703},{"grade":100,"solution":2086},{"grade":103,"solution":2039},{"grade":104,"solution":1871},{"grade":204,"solution":1842},{"grade":307,"solution":40},{"grade":1112,"solution":1893},{"grade":1216,"solution":1626}]},{"move":12,"grade":1112,"children":[{"grade":100,"solution":1187},{"grade":202,"solution":828},{"grade":204,"solution":789},{"grade":1120,"solution":146},{"grade":1140,"solution":2272},{"grade":2160,"solution":2169}]},{"move":40,"grade":1120,"children":[{"grade":204,"solution":1532},{"grade":307,"solution":1148},{"grade":408,"solution":375}]},{"move":1898,"grade":1121,"children":[{"grade":0,"solution":802},{"grade":102,"solution":397},{"grade":203,"move":1031,"children":[{"grade":5100,"solution":1031},{"grade":4060,"solution":1271}]},{"grade":1000,"solution":2269},{"grade":1040,"solution":1913},{"grade":1243,"solution":1655},{"grade":2010,"solution":2117}]},{"grade":1123,"move":768,"children":[{"grade":5100,"solution":768},{"grade":1124,"solution":2280}]},{"move":4,"grade":1124,"children":[{"grade":1124,"solution":2196},{"grade":2060,"solution":1063},{"grade":3090,"solution":1876}]},{"move":152,"grade":1142,"children":[{"grade":100,"move":1072,"children":[{"grade":5100,"solution":1072},{"grade":3273,"solution":2009}]},{"grade":202,"solution":2055},{"grade":204,"solution":723},{"grade":307,"solution":1239},{"grade":1000,"solution":1074}]},{"move":420,"grade":1203,"children":[{"grade":0,"solution":546},{"grade":100,"solution":1087},{"grade":102,"solution":1416},{"grade":103,"solution":112}]},{"grade":1205,"move":945,"children":[{"grade":5100,"solution":945},{"grade":2233,"solution":2259}]},{"move":20,"grade":1206,"children":[{"grade":103,"solution":1475},{"grade":207,"solution":1045},{"grade":1030,"solution":236},{"grade":2070,"solution":176}]},{"grade":1212,"solution":317},{"move":372,"grade":1215,"children":[{"grade":204,"solution":1678},{"grade":305,"solution":537},{"grade":407,"solution":509},{"grade":1140,"solution":516},{"grade":1241,"solution":2303}]},{"grade":1221,"move":603,"children":[{"grade":5100,"solution":603},{"grade":4090,"solution":906}]},{"move":10,"grade":1223,"children":[{"grade":2151,"solution":925},{"grade":3060,"solution":1285},{"grade":4164,"solution":21},{"grade":5100,"solution":10}]},{"grade":1224,"move":308,"children":[{"grade":5100,"solution":308},{"grade":1223,"solution":689}]},{"grade":1225,"move":1591,"children":[{"grade":5100,"solution":1591},{"grade":4100,"solution":2057}]},{"grade":1227,"move":1413,"children":[{"grade":5100,"solution":1413},{"grade":4164,"solution":1928}]},{"move":8,"grade":1243,"children":[{"grade":1231,"solution":1603},{"grade":1333,"solution":2006},{"grade":1335,"solution":965}]},{"grade":1306,"move":2028,"children":[{"grade":5100,"solution":2028},{"grade":4090,"solution":2161}]},{"grade":1307,"move":264,"children":[{"grade":5100,"solution":264},{"grade":3144,"solution":1339}]},{"move":456,"grade":1309,"children":[{"grade":0,"move":1713,"children":[{"grade":5100,"solution":1713},{"grade":4164,"solution":2056}]},{"grade":100,"solution":598},{"grade":103,"solution":1616},{"grade":1040,"solution":439}]},{"grade":1324,"move":1707,"children":[{"grade":5100,"solution":1707},{"grade":4090,"solution":1855}]},{"grade":1325,"solution":1573},{"move":54,"grade":1327,"children":[{"grade":0,"solution":1457},{"grade":100,"solution":1356},{"grade":1141,"solution":1510}]},{"grade":1328,"solution":592},{"grade":1346,"solution":1582},{"grade":1428,"solution":1279},{"move":4,"grade":2020,"children":[{"grade":2124,"move":7,"children":[{"grade":5100,"solution":7},{"grade":2227,"solution":2018}]},{"grade":2225,"solution":1244},{"grade":2227,"solution":855},{"grade":3060,"solution":875},{"grade":3134,"solution":1528},{"grade":5100,"solution":4}]},{"grade":2030,"move":745,"children":[{"grade":5100,"solution":745},{"grade":2030,"solution":1362}]},{"move":3908,"grade":2060,"children":[{"grade":0,"solution":2017},{"grade":100,"solution":1260},{"grade":101,"solution":1254},{"grade":102,"solution":2166},{"grade":103,"solution":1248},{"grade":204,"solution":2060},{"grade":1000,"solution":2090},{"grade":1010,"solution":624},{"grade":1030,"solution":1020},{"grade":1130,"solution":1383},{"grade":2030,"solution":1033}]},{"move":2318,"grade":2112,"children":[{"grade":206,"solution":1784},{"grade":309,"solution":1585},{"grade":407,"solution":1274},{"grade":1142,"solution":1767},{"grade":1242,"solution":609},{"grade":1343,"solution":303},{"grade":1346,"solution":1019}]},{"move":1332,"grade":2121,"children":[{"grade":103,"solution":485},{"grade":1030,"solution":1891},{"grade":1130,"solution":1052},{"grade":2040,"solution":1797},{"grade":2070,"move":1344,"children":[{"grade":5100,"solution":1344},{"grade":4090,"solution":2066}]},{"grade":3080,"solution":2258}]},{"grade":2123,"move":18,"children":[{"grade":5100,"solution":18},{"grade":3134,"solution":1576}]},{"grade":2124,"move":26,"children":[{"grade":5100,"solution":26},{"grade":3134,"solution":352}]},{"grade":2130,"solution":1941},{"grade":2132,"solution":364},{"grade":2134,"solution":1167},{"grade":2142,"solution":348},{"grade":2152,"move":607,"children":[{"grade":5100,"solution":607},{"grade":4080,"solution":1468}]},{"grade":2161,"move":290,"children":[{"grade":5100,"solution":290},{"grade":2263,"solution":1527}]},{"grade":2163,"move":753,"children":[{"grade":5100,"solution":753},{"grade":2263,"solution":1183}]},{"grade":2215,"solution":1553},{"grade":2224,"move":1235,"children":[{"grade":5100,"solution":1235},{"grade":4060,"solution":1559}]},{"grade":2225,"solution":1597},{"grade":2227,"solution":269},{"grade":2233,"move":721,"children":[{"grade":5100,"solution":721},{"grade":3134,"solution":1985}]},{"grade":2243,"solution":1895},{"grade":2245,"solution":272},{"grade":2264,"solution":1744},{"grade":3030,"solution":1473},{"move":676,"grade":3060,"children":[{"grade":0,"solution":1584},{"grade":100,"solution":501},{"move":152,"grade":104,"children":[{"grade":100,"solution":1207},{"grade":204,"solution":2308},{"grade":1110,"solution":243}]},{"grade":204,"solution":651},{"grade":206,"solution":301},{"grade":1030,"solution":1483}]},{"grade":3070,"move":283,"children":[{"grade":5100,"solution":283},{"grade":4070,"solution":1743}]},{"move":36,"grade":3090,"children":[{"grade":0,"move":694,"children":[{"grade":5100,"solution":694},{"grade":3090,"solution":2220}]},{"grade":102,"solution":34},{"grade":103,"solution":638},{"grade":1103,"solution":57}]},{"grade":3163,"solution":1263},{"grade":3173,"solution":1154},{"grade":3264,"solution":872},{"grade":4070,"solution":1537},{"move":152,"grade":4090,"children":[{"grade":100,"solution":2050},{"grade":204,"solution":1899},{"grade":1110,"solution":1242}]},{"grade":4100,"move":393,"children":[{"grade":5100,"solution":393},{"grade":4100,"solution":1934}]},{"grade":5100,"solution":522}]},{"move":4874,"grade":102,"children":[{"move":6,"grade":0,"children":[{"grade":103,"solution":2176},{"grade":1030,"solution":852},{"grade":1134,"solution":2186}]},{"grade":100,"move":940,"children":[{"grade":5100,"solution":940},{"grade":2245,"solution":2109}]},{"grade":102,"move":355,"children":[{"grade":5100,"solution":355},{"grade":2070,"solution":530}]},{"move":10,"grade":103,"children":[{"grade":0,"solution":1132},{"grade":1104,"solution":488},{"grade":1205,"solution":585}]},{"grade":104,"solution":672},{"grade":202,"solution":1517},{"grade":204,"move":831,"children":[{"grade":5100,"solution":831},{"grade":4070,"solution":1485}]},{"grade":205,"move":1682,"children":[{"grade":5100,"solution":1682},{"grade":305,"solution":2040}]},{"grade":206,"solution":538},{"grade":306,"solution":330},{"grade":1000,"solution":759},{"grade":1010,"move":711,"children":[{"grade":5100,"solution":711},{"grade":2050,"solution":1794}]},{"grade":1020,"solution":2212},{"move":12,"grade":1030,"children":[{"grade":0,"solution":2140},{"grade":103,"solution":915},{"grade":104,"solution":2198},{"grade":207,"solution":1715}]},{"grade":1040,"solution":1849},{"grade":1102,"move":858,"children":[{"grade":5100,"solution":858},{"grade":4090,"solution":879}]},{"grade":1103,"solution":133},{"grade":1104,"move":399,"children":[{"grade":5100,"solution":399},{"grade":4060,"solution":2058}]},{"grade":1112,"solution":1980},{"grade":1120,"solution":87},{"grade":1131,"move":583,"children":[{"grade":5100,"solution":583},{"grade":4100,"solution":683}]},{"grade":1134,"solution":910},{"grade":1143,"solution":962},{"grade":1206,"move":1161,"children":[{"grade":5100,"solution":1161},{"grade":4070,"solution":1914}]},{"grade":1243,"solution":1892},{"grade":2010,"move":361,"children":[{"grade":5100,"solution":361},{"grade":3050,"solution":2068}]},{"grade":2040,"solution":244},{"grade":2050,"solution":454},{"grade":2132,"solution":1224},{"move":3580,"grade":2134,"children":[{"grade":2030,"solution":2205},{"grade":2131,"solution":2304},{"grade":2132,"solution":966},{"grade":3070,"solution":770}]},{"grade":2140,"move":995,"children":[{"grade":5100,"solution":995},{"grade":4100,"solution":1702}]},{"grade":3050,"solution":1809}]},{"move":5048,"grade":103,"children":[{"move":1410,"grade":101,"children":[{"grade":103,"solution":1511},{"grade":204,"solution":557},{"grade":205,"solution":1653},{"grade":306,"solution":547},{"grade":309,"solution":1304},{"grade":1123,"solution":812},{"grade":1143,"solution":1541},{"grade":1245,"solution":805},{"grade":1306,"solution":2013}]},{"grade":201,"move":1912,"children":[{"grade":5100,"solution":1912},{"grade":2163,"solution":2084}]},{"move":232,"grade":203,"children":[{"grade":1212,"solution":955},{"grade":1221,"solution":1332},{"grade":1325,"solution":889},{"grade":2112,"solution":937},{"grade":2130,"solution":1158},{"grade":2261,"solution":1013},{"grade":3030,"solution":1025},{"grade":4070,"move":245,"children":[{"grade":5100,"solution":245},{"grade":4070,"solution":252}]},{"grade":5100,"solution":232}]},{"move":22,"grade":204,"children":[{"grade":100,"solution":1526},{"grade":101,"solution":762},{"grade":201,"solution":1558},{"grade":1010,"solution":1556}]},{"move":236,"grade":205,"children":[{"grade":201,"solution":929},{"grade":305,"solution":2260},{"grade":1000,"solution":307},{"grade":1101,"solution":920},{"grade":1102,"solution":1897},{"grade":1203,"solution":1425},{"grade":1205,"solution":47},{"grade":3050,"solution":1174}]},{"grade":303,"move":696,"children":[{"grade":5100,"solution":696},{"grade":1324,"solution":1402}]},{"grade":304,"move":14,"children":[{"grade":5100,"solution":14},{"grade":3133,"solution":1827}]},{"move":550,"grade":305,"children":[{"grade":101,"solution":1290},{"grade":1010,"solution":1993},{"grade":1112,"solution":545},{"grade":1216,"solution":374},{"grade":2010,"solution":1302},{"grade":2040,"solution":1329},{"grade":2142,"solution":1698}]},{"move":14,"grade":306,"children":[{"grade":2030,"solution":1496},{"grade":3030,"solution":743},{"grade":4070,"solution":2122}]},{"move":202,"grade":307,"children":[{"grade":103,"solution":1185},{"grade":304,"solution":2227},{"grade":1030,"solution":309},{"grade":1130,"solution":1395},{"grade":1243,"solution":507},{"grade":1244,"solution":660},{"grade":2070,"solution":691},{"grade":3080,"solution":990}]},{"move":352,"grade":308,"children":[{"grade":1000,"solution":2012},{"grade":1101,"solution":581},{"grade":1104,"solution":1712},{"grade":1205,"solution":1845},{"grade":2010,"solution":1983},{"grade":2030,"solution":2210},{"grade":2131,"solution":2264}]},{"grade":407,"solution":1090},{"grade":408,"solution":486},{"move":12,"grade":1010,"children":[{"grade":0,"solution":1608},{"grade":205,"solution":1171},{"grade":206,"solution":676}]},{"move":6484,"grade":1101,"children":[{"grade":0,"solution":2292},{"grade":100,"solution":1910},{"grade":103,"solution":665},{"grade":1110,"solution":705},{"grade":1130,"move":228,"children":[{"grade":5100,"solution":228},{"grade":4060,"solution":1205}]},{"grade":1214,"solution":1194},{"grade":1231,"solution":1665},{"grade":2170,"solution":1000}]},{"grade":1110,"solution":1247},{"move":6,"grade":1112,"children":[{"grade":1000,"solution":970},{"grade":1103,"solution":649},{"grade":1140,"solution":838}]},{"grade":1114,"move":271,"children":[{"grade":5100,"solution":271},{"grade":1110,"solution":1106}]},{"move":416,"grade":1131,"children":[{"grade":0,"solution":654},{"grade":102,"solution":2141},{"grade":104,"solution":1999},{"grade":1212,"solution":195},{"grade":2010,"solution":1969}]},{"grade":1141,"solution":679},{"move":584,"grade":1203,"children":[{"grade":101,"solution":1008},{"grade":201,"solution":608},{"grade":203,"solution":667},{"grade":306,"solution":1407}]},{"move":20,"grade":1204,"children":[{"grade":0,"solution":1184},{"grade":101,"solution":214},{"grade":203,"solution":1529}]},{"grade":1205,"move":16,"children":[{"grade":5100,"solution":16},{"grade":2121,"solution":312}]},{"grade":1213,"solution":724},{"grade":1214,"move":814,"children":[{"grade":5100,"solution":814},{"grade":3142,"solution":2289}]},{"grade":1216,"solution":1978},{"grade":1217,"solution":505},{"grade":1231,"solution":1628},{"move":30,"grade":1235,"children":[{"grade":303,"solution":742},{"grade":2020,"solution":1049},{"grade":2124,"solution":1954},{"grade":3030,"solution":1055}]},{"grade":1243,"move":706,"children":[{"grade":5100,"solution":706},{"grade":3161,"solution":1337}]},{"grade":1306,"solution":880},{"grade":1317,"solution":502},{"grade":1335,"solution":526},{"grade":1343,"solution":677},{"grade":2010,"move":523,"children":[{"grade":5100,"solution":523},{"grade":3040,"solution":1030}]},{"grade":2030,"move":874,"children":[{"grade":5100,"solution":874},{"grade":3060,"solution":2193}]},{"grade":2040,"move":974,"children":[{"grade":5100,"solution":974},{"grade":3080,"solution":2261}]},{"grade":2050,"solution":584},{"grade":2114,"move":1261,"children":[{"grade":5100,"solution":1261},{"grade":3142,"solution":1696}]},{"grade":2130,"solution":935},{"grade":2131,"solution":370},{"grade":2134,"move":32,"children":[{"grade":5100,"solution":32},{"grade":3060,"solution":1866}]},{"grade":2141,"solution":503},{"grade":2171,"solution":836},{"grade":2225,"solution":95},{"grade":2235,"solution":518},{"grade":2242,"solution":980},{"grade":2244,"solution":2300},{"grade":2255,"solution":1759},{"grade":3030,"solution":1857},{"grade":3040,"solution":425},{"grade":3255,"solution":2236},{"grade":4060,"solution":438}]},{"move":3418,"grade":104,"children":[{"move":170,"grade":0,"children":[{"grade":205,"solution":2171},{"grade":1114,"solution":1882},{"grade":1141,"solution":1113},{"grade":1214,"solution":2241},{"grade":1217,"solution":1341},{"grade":2144,"solution":1105}]},{"grade":100,"solution":1281},{"move":22,"grade":101,"children":[{"grade":102,"solution":971},{"grade":1102,"solution":2065},{"grade":2020,"solution":2073},{"grade":2060,"solution":2214}]},{"move":114,"grade":102,"children":[{"grade":0,"solution":1927},{"grade":101,"solution":908},{"grade":103,"solution":1351},{"grade":104,"solution":2118},{"grade":206,"solution":2177},{"grade":207,"solution":141},{"grade":1040,"solution":1562}]},{"move":6990,"grade":103,"children":[{"grade":0,"solution":1745},{"grade":101,"solution":1672},{"grade":103,"solution":1412},{"grade":104,"solution":543},{"grade":204,"solution":170},{"grade":206,"solution":1377},{"grade":1040,"solution":2277},{"grade":1113,"solution":860},{"grade":2030,"solution":1765}]},{"grade":202,"move":119,"children":[{"grade":5100,"solution":119},{"grade":4060,"solution":380}]},{"move":14,"grade":203,"children":[{"grade":0,"solution":561},{"grade":100,"solution":708},{"grade":101,"solution":591},{"grade":3070,"solution":1324}]},{"grade":204,"move":403,"children":[{"grade":5100,"solution":403},{"grade":1224,"solution":1878}]},{"grade":205,"solution":1884},{"grade":1000,"move":1542,"children":[{"grade":5100,"solution":1542},{"grade":2123,"solution":2297}]},{"move":10,"grade":1020,"children":[{"grade":0,"solution":760},{"grade":204,"solution":1321},{"grade":1030,"solution":2049}]},{"grade":1030,"solution":531},{"grade":1040,"move":17,"children":[{"grade":5100,"solution":17},{"grade":4080,"solution":887}]},{"grade":1101,"solution":953},{"grade":1102,"solution":1783},{"grade":1103,"solution":600},{"grade":1112,"solution":1303},{"grade":1113,"solution":1521},{"grade":1120,"solution":559},{"grade":1121,"solution":185},{"grade":1130,"solution":1128},{"grade":1132,"solution":267},{"grade":1141,"solution":118},{"grade":1142,"solution":2163},{"grade":1205,"solution":1896},{"grade":1233,"solution":1326},{"grade":1242,"solution":328},{"grade":1244,"solution":924},{"grade":2050,"move":343,"children":[{"grade":5100,"solution":343},{"grade":4060,"solution":1050}]},{"grade":2150,"solution":1111},{"grade":2170,"solution":1657}]},{"move":6272,"grade":201,"children":[{"move":9306,"grade":102,"children":[{"grade":102,"move":1569,"children":[{"grade":5100,"solution":1569},{"grade":1410,"solution":1960}]},{"grade":205,"move":241,"children":[{"grade":5100,"solution":241},{"grade":2227,"solution":1431}]},{"grade":306,"solution":1103},{"grade":406,"solution":2283},{"grade":1020,"move":13,"children":[{"grade":5100,"solution":13},{"grade":3050,"solution":318}]},{"grade":1102,"solution":1959},{"grade":1123,"solution":1768},{"grade":1203,"solution":1175},{"grade":1224,"solution":1862},{"grade":1328,"solution":366},{"grade":2020,"solution":27},{"grade":2060,"solution":1968},{"grade":3060,"solution":81}]},{"move":132,"grade":202,"children":[{"grade":102,"solution":2204},{"grade":203,"solution":238},{"grade":1020,"solution":1110},{"grade":1120,"solution":1126},{"grade":2050,"solution":2302},{"grade":2060,"solution":1605}]},{"grade":203,"move":653,"children":[{"grade":5100,"solution":653},{"grade":1227,"solution":1923}]},{"move":1156,"grade":205,"children":[{"grade":206,"solution":1593},{"grade":307,"solution":2114},{"grade":410,"solution":1165},{"grade":1124,"solution":1988},{"grade":1142,"solution":854},{"grade":1242,"solution":1125},{"grade":3070,"solution":1009}]},{"grade":206,"solution":2081},{"grade":305,"solution":2278},{"grade":409,"solution":978},{"move":3514,"grade":1020,"children":[{"grade":103,"move":1396,"children":[{"grade":5100,"solution":1396},{"grade":2030,"solution":1515}]},{"grade":203,"solution":11},{"grade":205,"solution":791},{"grade":1103,"solution":669},{"grade":1130,"move":930,"children":[{"grade":5100,"solution":930},{"grade":3090,"solution":1825}]},{"grade":1131,"solution":1908},{"grade":1231,"solution":1697},{"grade":2030,"solution":1670},{"grade":2040,"move":1177,"children":[{"grade":5100,"solution":1177},{"grade":4060,"solution":2014}]},{"grade":2070,"solution":1921},{"grade":2140,"solution":1146},{"grade":2171,"solution":704},{"grade":2172,"solution":830},{"grade":2245,"solution":1916},{"grade":4080,"solution":1815}]},{"grade":1102,"move":1189,"children":[{"grade":5100,"solution":1189},{"grade":1410,"solution":1349}]},{"grade":1120,"move":38,"children":[{"grade":5100,"solution":38},{"grade":3090,"solution":1266}]},{"move":4,"grade":1121,"children":[{"grade":1124,"solution":527},{"grade":1225,"solution":1865},{"grade":2154,"solution":1140}]},{"move":172,"grade":1123,"children":[{"grade":306,"move":1192,"children":[{"grade":5100,"solution":1192},{"grade":3134,"solution":1991}]},{"grade":1233,"move":234,"children":[{"grade":5100,"solution":234},{"grade":3050,"solution":2088}]},{"grade":1333,"solution":1486},{"grade":1346,"solution":1607},{"grade":2273,"solution":988},{"grade":2373,"solution":184}]},{"grade":1124,"solution":618},{"grade":1132,"solution":842},{"move":30,"grade":1142,"children":[{"grade":103,"solution":284},{"grade":207,"solution":1671},{"grade":1113,"solution":928}]},{"grade":1205,"move":558,"children":[{"grade":5100,"solution":558},{"grade":4070,"solution":1557}]},{"grade":1212,"solution":2306},{"grade":1215,"move":1246,"children":[{"grade":5100,"solution":1246},{"grade":2217,"solution":1634}]},{"grade":1216,"solution":489},{"grade":1221,"solution":1971},{"grade":1223,"solution":1096},{"move":14,"grade":1224,"children":[{"grade":103,"solution":1933},{"grade":1040,"solution":1632},{"grade":1141,"solution":715}]},{"move":30,"grade":1225,"children":[{"grade":103,"solution":1451},{"grade":204,"solution":229},{"grade":207,"solution":1420}]},{"grade":1232,"solution":1776},{"grade":1245,"solution":967},{"grade":1324,"solution":909},{"grade":1328,"solution":998},{"move":30,"grade":2020,"children":[{"grade":103,"solution":418},{"grade":207,"solution":1685},{"grade":1131,"solution":1309}]},{"grade":2030,"solution":949},{"move":146,"grade":2050,"children":[{"grade":103,"solution":1163},{"grade":203,"solution":62},{"grade":204,"move":1014,"children":[{"grade":5100,"solution":1014},{"grade":3160,"solution":1272}]},{"grade":1103,"solution":188},{"grade":1113,"solution":1138},{"grade":1205,"solution":1134},{"grade":1245,"solution":1245}]},{"grade":2060,"solution":261},{"grade":2121,"move":84,"children":[{"grade":5100,"solution":84},{"grade":4173,"solution":147}]},{"grade":2133,"solution":1516},{"grade":2134,"solution":1411},{"grade":2150,"solution":1802},{"grade":2152,"solution":1708},{"grade":2234,"solution":316},{"grade":3030,"solution":1104},{"grade":3090,"solution":1837},{"grade":4090,"solution":650}]},{"move":1742,"grade":202,"children":[{"grade":103,"move":319,"children":[{"grade":5100,"solution":319},{"grade":406,"solution":477}]},{"grade":203,"solution":383},{"grade":205,"solution":436},{"move":12,"grade":1030,"children":[{"grade":103,"solution":1963},{"grade":207,"solution":1129},{"grade":1103,"solution":127}]},{"move":506,"grade":1103,"children":[{"grade":1207,"solution":1379},{"grade":1308,"solution":1656},{"grade":1309,"solution":97},{"grade":2245,"solution":204}]},{"grade":1123,"move":1781,"children":[{"grade":5100,"solution":1781},{"grade":2255,"solution":2216}]},{"grade":1130,"move":85,"children":[{"grade":5100,"solution":85},{"grade":4100,"solution":1965}]},{"grade":1131,"solution":1318},{"grade":1132,"solution":1490},{"grade":1204,"solution":562},{"grade":1205,"solution":2003},{"grade":1231,"solution":1717},{"grade":1236,"solution":144},{"grade":2030,"solution":506},{"grade":2040,"solution":1555},{"grade":2050,"solution":1277},{"grade":2123,"solution":156},{"grade":2134,"solution":1297},{"grade":2150,"solution":433},{"grade":2245,"solution":277},{"grade":3060,"move":225,"children":[{"grade":5100,"solution":225},{"grade":3160,"solution":1108}]},{"grade":3080,"solution":1084}]},{"move":374,"grade":203,"children":[{"move":132,"grade":0,"children":[{"grade":0,"solution":2203},{"grade":100,"solution":149},{"grade":101,"solution":922},{"grade":103,"solution":1044},{"grade":104,"solution":379},{"grade":204,"solution":1255},{"grade":308,"solution":1284},{"grade":1010,"solution":825},{"grade":1101,"solution":1984}]},{"grade":100,"solution":963},{"move":86,"grade":101,"children":[{"grade":206,"solution":435},{"grade":1124,"solution":209},{"grade":1142,"solution":1100},{"grade":1227,"solution":2082},{"grade":2154,"solution":1990}]},{"move":92,"grade":102,"children":[{"grade":102,"solution":2146},{"grade":203,"solution":239},{"grade":205,"solution":59},{"grade":206,"solution":1249},{"grade":1142,"solution":1085},{"grade":1215,"solution":446}]},{"move":98,"grade":103,"children":[{"grade":0,"solution":93},{"grade":101,"solution":594},{"grade":204,"solution":1568},{"grade":1101,"solution":2234}]},{"move":8,"grade":104,"children":[{"grade":304,"solution":337},{"grade":308,"solution":2116},{"grade":1131,"solution":1429}]},{"grade":201,"solution":1618},{"grade":202,"solution":2256},{"move":36,"grade":203,"children":[{"grade":0,"solution":1548},{"grade":100,"solution":2077},{"grade":206,"solution":2008},{"grade":1030,"solution":2262}]},{"grade":204,"solution":1484},{"grade":303,"move":310,"children":[{"grade":5100,"solution":310},{"grade":1307,"solution":2301}]},{"grade":306,"solution":1560},{"grade":406,"move":440,"children":[{"grade":5100,"solution":440},{"grade":3246,"solution":1276}]},{"move":448,"grade":1000,"children":[{"grade":1207,"move":390,"children":[{"grade":5100,"solution":390},{"grade":3163,"solution":1092}]},{"grade":2134,"solution":324},{"grade":2143,"solution":1543},{"grade":3070,"solution":1286},{"grade":3153,"solution":2091},{"grade":4090,"solution":2157},{"grade":5100,"solution":448}]},{"move":206,"grade":1020,"children":[{"grade":1123,"solution":2181},{"grade":2050,"move":849,"children":[{"grade":5100,"solution":849},{"grade":2050,"solution":1875}]},{"grade":2123,"solution":504},{"grade":2133,"solution":173},{"grade":2150,"solution":1823},{"grade":3060,"solution":1690},{"grade":3090,"solution":1819},{"grade":4060,"solution":373},{"grade":5100,"solution":206}]},{"grade":1030,"solution":1037},{"grade":1040,"solution":1188},{"grade":1102,"solution":614},{"grade":1103,"solution":1262},{"grade":1104,"solution":1173},{"move":354,"grade":1120,"children":[{"grade":103,"solution":1347},{"grade":207,"solution":2042},{"grade":309,"solution":726},{"grade":1134,"solution":1777},{"grade":1143,"solution":2170}]},{"move":22,"grade":1121,"children":[{"grade":103,"solution":800},{"grade":203,"solution":1064},{"grade":1030,"solution":61},{"grade":1134,"solution":1880},{"grade":1143,"solution":1230}]},{"grade":1123,"solution":365},{"grade":1124,"move":480,"children":[{"grade":5100,"solution":480},{"grade":4060,"solution":851}]},{"grade":1130,"solution":1648},{"grade":1221,"solution":1778},{"grade":1225,"solution":877},{"grade":1227,"solution":1545},{"grade":1242,"solution":2087},{"grade":1243,"solution":1785},{"grade":2010,"solution":102},{"move":2964,"grade":2020,"children":[{"grade":0,"solution":451},{"grade":101,"solution":2185},{"grade":102,"solution":1428},{"grade":1010,"solution":30},{"grade":1040,"solution":64},{"grade":1142,"solution":259},{"grade":2050,"solution":1506}]},{"grade":2030,"solution":798},{"grade":2060,"move":72,"children":[{"grade":5100,"solution":72},{"grade":3070,"solution":1201}]},{"grade":2121,"move":1770,"children":[{"grade":5100,"solution":1770},{"grade":4090,"solution":1820}]},{"grade":2123,"solution":948},{"grade":2141,"solution":749},{"grade":2161,"move":1489,"children":[{"grade":5100,"solution":1489},{"grade":4070,"solution":2284}]},{"grade":3030,"move":406,"children":[{"grade":5100,"solution":406},{"grade":4164,"solution":687}]},{"grade":3060,"move":212,"children":[{"grade":5100,"solution":212},{"grade":4070,"solution":1296}]},{"grade":3090,"solution":1554}]},{"move":9040,"grade":204,"children":[{"move":2568,"grade":0,"children":[{"grade":205,"solution":431},{"grade":308,"solution":1938},{"grade":410,"solution":1766},{"grade":1114,"move":50,"children":[{"grade":5100,"solution":50},{"grade":3180,"solution":1112}]},{"grade":1214,"solution":702},{"grade":1217,"move":495,"children":[{"grade":5100,"solution":495},{"grade":1215,"solution":2043}]},{"grade":1243,"solution":1704},{"grade":2050,"solution":2033},{"grade":2144,"solution":1946},{"grade":2152,"solution":1583},{"grade":2153,"solution":1226},{"grade":2171,"solution":2209},{"grade":2243,"solution":2104},{"grade":2253,"solution":2165},{"grade":3050,"solution":1647},{"grade":3070,"solution":1976}]},{"grade":100,"move":1382,"children":[{"grade":5100,"solution":1382},{"grade":2134,"solution":2285}]},{"move":8,"grade":101,"children":[{"grade":204,"solution":1127},{"grade":408,"solution":1660},{"grade":1131,"solution":1654},{"grade":1235,"solution":821},{"grade":1308,"solution":764},{"grade":2131,"solution":1830}]},{"grade":102,"move":1081,"children":[{"grade":5100,"solution":1081},{"grade":406,"solution":1293}]},{"move":8,"grade":103,"children":[{"grade":204,"solution":1057},{"grade":304,"solution":472},{"grade":308,"move":542,"children":[{"grade":5100,"solution":542},{"grade":2337,"solution":905}]},{"grade":406,"solution":886},{"grade":408,"solution":423},{"grade":1131,"solution":1536},{"grade":1204,"solution":2187},{"grade":1233,"solution":911},{"grade":2273,"solution":942}]},{"grade":104,"move":407,"children":[{"grade":5100,"solution":407},{"grade":2217,"solution":1116}]},{"move":8,"grade":201,"children":[{"grade":204,"solution":2240},{"grade":308,"solution":827},{"grade":1235,"solution":1966}]},{"grade":202,"solution":2093},{"grade":203,"solution":484},{"grade":204,"solution":192},{"grade":205,"solution":870},{"grade":305,"solution":796},{"grade":306,"solution":840},{"move":36,"grade":1000,"children":[{"grade":0,"move":1726,"children":[{"grade":5100,"solution":1726},{"grade":2113,"solution":2228}]},{"grade":100,"solution":479},{"grade":103,"solution":2035},{"grade":204,"solution":91},{"grade":205,"solution":1388}]},{"move":4,"grade":1010,"children":[{"grade":206,"solution":931},{"grade":1124,"solution":553},{"grade":1142,"solution":1856}]},{"grade":1020,"solution":720},{"grade":1030,"solution":1354},{"grade":1040,"move":1493,"children":[{"grade":5100,"solution":1493},{"grade":4100,"solution":1688}]},{"grade":1101,"solution":475},{"grade":1120,"solution":1497},{"grade":1121,"move":1011,"children":[{"grade":5100,"solution":1011},{"grade":4100,"solution":1831}]},{"grade":1123,"solution":1613},{"grade":1132,"solution":2221},{"grade":1140,"solution":674},{"grade":1205,"solution":1951},{"grade":1224,"move":1538,"children":[{"grade":5100,"solution":1538},{"grade":4100,"solution":2226}]},{"grade":1232,"solution":158},{"grade":1235,"solution":1018},{"grade":2010,"solution":1295},{"grade":2040,"move":1579,"children":[{"grade":5100,"solution":1579},{"grade":2245,"solution":2213}]},{"grade":2050,"solution":2288},{"grade":2060,"solution":1016},{"grade":2132,"solution":560},{"grade":3090,"solution":157}]},{"move":10698,"grade":205,"children":[{"grade":0,"solution":1989},{"grade":100,"solution":1782},{"grade":101,"solution":452},{"move":1726,"grade":102,"children":[{"grade":207,"solution":569},{"grade":1030,"solution":402},{"grade":1130,"solution":1637},{"grade":1134,"solution":1651},{"move":182,"grade":1234,"children":[{"grade":309,"solution":265},{"grade":409,"solution":1644},{"grade":410,"solution":2287}]},{"grade":1336,"solution":2156},{"grade":2070,"solution":1298},{"grade":2134,"solution":2041},{"grade":2170,"solution":113}]},{"move":12,"grade":103,"children":[{"grade":100,"solution":1550},{"grade":202,"solution":109},{"grade":203,"solution":1469}]},{"move":22,"grade":201,"children":[{"grade":102,"solution":1333},{"grade":1102,"solution":1761},{"grade":1142,"solution":19}]},{"grade":202,"move":1577,"children":[{"grade":5100,"solution":1577},{"grade":1224,"solution":2192}]},{"grade":203,"move":1012,"children":[{"grade":5100,"solution":1012},{"grade":1233,"solution":1919}]},{"grade":205,"solution":1433},{"grade":206,"solution":1051},{"grade":1000,"solution":1664},{"move":266,"grade":1010,"children":[{"grade":100,"solution":1447},{"grade":103,"solution":1753},{"grade":202,"solution":813},{"grade":1030,"solution":2249},{"grade":1040,"solution":2121},{"grade":1132,"solution":787},{"grade":1140,"solution":1500}]},{"move":4,"grade":1020,"children":[{"grade":1225,"solution":1258},{"grade":1328,"solution":221},{"grade":2161,"solution":110}]},{"grade":1101,"solution":856},{"grade":1102,"solution":190},{"grade":1103,"solution":582},{"grade":1104,"solution":2080},{"move":54,"grade":1110,"children":[{"grade":0,"solution":2120},{"grade":100,"solution":2235},{"grade":1141,"solution":335}]},{"grade":1113,"solution":92},{"grade":1114,"solution":180},{"move":120,"grade":1120,"children":[{"grade":0,"solution":1073},{"grade":100,"solution":1905},{"grade":1000,"solution":2147},{"grade":1040,"solution":181}]},{"grade":1121,"solution":1612},{"grade":1142,"move":782,"children":[{"grade":5100,"solution":782},{"grade":2263,"solution":1415}]},{"grade":1203,"solution":1575},{"grade":1221,"solution":1102},{"grade":1223,"solution":2250},{"grade":1306,"solution":663},{"grade":2020,"solution":2293},{"grade":2030,"solution":1172},{"grade":2040,"move":128,"children":[{"grade":5100,"solution":128},{"grade":3160,"solution":991}]},{"move":328,"grade":2050,"children":[{"grade":0,"solution":1711},{"grade":102,"solution":487},{"grade":1010,"solution":389},{"grade":1030,"solution":1162},{"grade":2050,"solution":296}]},{"move":148,"grade":2060,"children":[{"grade":0,"solution":873},{"grade":101,"solution":1440},{"grade":102,"solution":628},{"grade":104,"solution":2270}]},{"grade":2142,"solution":2026},{"grade":2161,"solution":1877},{"move":30,"grade":2163,"children":[{"grade":0,"solution":1520},{"grade":101,"solution":483},{"grade":104,"solution":1359}]},{"grade":3050,"solution":738},{"grade":3060,"solution":1225},{"grade":3070,"solution":1874},{"grade":3080,"solution":1986},{"grade":3090,"solution":610},{"grade":3163,"solution":1686}]},{"grade":206,"move":536,"children":[{"grade":5100,"solution":536},{"grade":1141,"solution":2265}]},{"move":1212,"grade":207,"children":[{"move":16,"grade":0,"children":[{"grade":1020,"solution":1036},{"grade":1132,"solution":2113},{"grade":2050,"solution":748},{"grade":3090,"solution":597}]},{"grade":100,"solution":1918},{"grade":101,"move":76,"children":[{"grade":5100,"solution":76},{"grade":306,"solution":1790}]},{"grade":102,"solution":496},{"grade":103,"move":725,"children":[{"grade":5100,"solution":725},{"grade":1241,"solution":1604}]},{"grade":104,"solution":2188},{"grade":203,"move":799,"children":[{"grade":5100,"solution":799},{"grade":4070,"solution":954}]},{"move":214,"grade":205,"children":[{"grade":409,"solution":1445},{"grade":1232,"solution":1814},{"grade":1333,"solution":1967},{"grade":1336,"solution":1720}]},{"grade":1000,"solution":1942},{"grade":1010,"solution":1620},{"grade":1030,"solution":1699},{"grade":1040,"solution":103},{"grade":1102,"solution":391},{"grade":1103,"solution":434},{"grade":1130,"solution":1679},{"grade":1141,"solution":616},{"grade":1142,"move":177,"children":[{"grade":5100,"solution":177},{"grade":1446,"solution":818}]},{"grade":2040,"solution":1417},{"grade":2070,"solution":470},{"grade":2141,"solution":1621},{"grade":3090,"solution":1400}]},{"move":1544,"grade":303,"children":[{"grade":0,"move":1325,"children":[{"grade":5100,"solution":1325},{"grade":2163,"solution":2267}]},{"move":7346,"grade":102,"children":[{"grade":204,"solution":541},{"grade":304,"solution":15},{"grade":306,"solution":1079},{"grade":308,"solution":1250},{"grade":1113,"solution":70},{"grade":1131,"solution":843},{"grade":2171,"solution":1042}]},{"grade":103,"solution":1774},{"grade":104,"solution":1439},{"grade":202,"solution":478},{"grade":203,"solution":804},{"grade":205,"solution":926},{"grade":207,"solution":2051},{"grade":1000,"solution":2054},{"grade":1010,"solution":2102},{"grade":2010,"solution":1917}]},{"move":2042,"grade":304,"children":[{"grade":205,"move":1043,"children":[{"grade":5100,"solution":1043},{"grade":2170,"solution":1828}]},{"grade":305,"move":155,"children":[{"grade":5100,"solution":155},{"grade":4100,"solution":1422}]},{"grade":1123,"move":321,"children":[{"grade":5100,"solution":321},{"grade":3151,"solution":549}]},{"move":52,"grade":1132,"children":[{"grade":100,"solution":1939},{"grade":103,"solution":815},{"grade":203,"solution":322},{"grade":1000,"solution":357}]},{"grade":1205,"move":766,"children":[{"grade":5100,"solution":766},{"grade":4080,"solution":2182}]},{"grade":1223,"solution":1024},{"grade":1224,"solution":1662},{"grade":1232,"solution":63},{"grade":1233,"solution":866},{"grade":1328,"solution":1488},{"grade":2132,"solution":859},{"grade":2151,"solution":554},{"grade":2163,"solution":625},{"grade":2172,"solution":1879}]},{"move":6214,"grade":305,"children":[{"grade":0,"move":1367,"children":[{"grade":5100,"solution":1367},{"grade":3090,"solution":2045}]},{"grade":100,"solution":1069},{"grade":101,"solution":1844},{"move":40,"grade":102,"children":[{"grade":0,"solution":2128},{"grade":101,"solution":164},{"grade":103,"solution":604},{"grade":1020,"solution":142}]},{"move":4,"grade":103,"children":[{"grade":1124,"solution":2011},{"grade":1225,"solution":775},{"grade":1328,"solution":1663}]},{"grade":202,"solution":1023},{"grade":203,"solution":28},{"grade":204,"move":1460,"children":[{"grade":5100,"solution":1460},{"grade":4100,"solution":1961}]},{"grade":205,"solution":697},{"grade":207,"solution":1130},{"grade":307,"solution":1371},{"grade":1000,"move":167,"children":[{"grade":5100,"solution":167},{"grade":4090,"solution":187}]},{"grade":1030,"solution":1848},{"grade":1103,"move":179,"children":[{"grade":5100,"solution":179},{"grade":4060,"solution":2111}]},{"grade":1134,"solution":822},{"grade":1204,"solution":294},{"grade":2030,"solution":329},{"grade":2154,"solution":2127}]},{"move":390,"grade":306,"children":[{"grade":309,"solution":382},{"grade":1245,"solution":1133},{"grade":1346,"solution":698},{"grade":2172,"solution":555},{"grade":2227,"solution":2144},{"grade":3090,"solution":1499},{"grade":3172,"solution":1241}]},{"move":230,"grade":307,"children":[{"grade":0,"solution":1435},{"grade":100,"solution":1065},{"grade":103,"solution":1404},{"grade":202,"solution":471},{"grade":205,"solution":2202},{"grade":1040,"solution":216},{"grade":1142,"solution":623}]},{"move":52,"grade":308,"children":[{"grade":0,"solution":100},{"grade":100,"solution":2248},{"grade":103,"solution":210},{"grade":205,"solution":1606},{"grade":1000,"solution":246},{"grade":1130,"solution":2136}]},{"grade":309,"solution":761},{"grade":406,"move":2001,"children":[{"grade":5100,"solution":2001},{"grade":4100,"solution":2078}]},{"grade":407,"solution":636},{"grade":408,"solution":1147},{"move":8284,"grade":1000,"children":[{"move":12188,"grade":0,"children":[{"grade":103,"move":114,"children":[{"grade":5100,"solution":114},{"grade":2010,"solution":709}]},{"grade":203,"solution":1806},{"grade":204,"solution":1143},{"grade":205,"solution":784},{"grade":306,"solution":233},{"grade":1030,"move":289,"children":[{"grade":5100,"solution":289},{"grade":3144,"solution":1674}]},{"grade":1130,"solution":1633},{"grade":1131,"solution":1443},{"grade":1132,"solution":1807},{"grade":1134,"solution":1863},{"grade":1234,"solution":385},{"grade":1236,"solution":2142}]},{"move":8,"grade":100,"children":[{"grade":104,"solution":1221},{"grade":1040,"solution":2133},{"grade":2060,"solution":1348}]},{"move":7638,"grade":101,"children":[{"move":22,"grade":103,"children":[{"grade":205,"solution":1775},{"grade":309,"solution":1141},{"grade":1132,"solution":1615}]},{"grade":207,"solution":1687},{"move":430,"grade":1030,"children":[{"grade":0,"move":862,"children":[{"grade":5100,"solution":862},{"grade":3144,"solution":1222}]},{"grade":100,"solution":305},{"grade":101,"solution":894},{"grade":1040,"solution":1384}]},{"grade":1130,"solution":1444},{"grade":1131,"solution":432},{"grade":1132,"solution":78},{"grade":1231,"solution":900},{"grade":2050,"solution":2305},{"grade":2070,"solution":572},{"grade":2150,"solution":42},{"grade":2151,"solution":410},{"grade":2170,"solution":369},{"grade":3090,"solution":1121}]},{"grade":102,"move":1180,"children":[{"grade":5100,"solution":1180},{"grade":3144,"solution":2268}]},{"move":202,"grade":103,"children":[{"grade":102,"solution":590},{"grade":202,"solution":1432},{"grade":206,"solution":169},{"grade":2050,"solution":845}]},{"grade":104,"solution":1370},{"grade":201,"solution":1369},{"move":6,"grade":203,"children":[{"grade":0,"solution":1667},{"grade":103,"solution":247},{"grade":1030,"solution":1861}]},{"grade":204,"solution":1390},{"grade":205,"move":323,"children":[{"grade":5100,"solution":323},{"grade":2010,"solution":1932}]},{"move":6,"grade":207,"children":[{"grade":0,"solution":956},{"grade":100,"solution":1308},{"grade":1040,"solution":2206}]},{"grade":1010,"move":71,"children":[{"grade":5100,"solution":71},{"grade":2215,"solution":499}]},{"grade":1020,"move":570,"children":[{"grade":5100,"solution":570},{"grade":3133,"solution":1278}]},{"move":10982,"grade":1030,"children":[{"grade":102,"solution":1088},{"grade":202,"solution":447},{"grade":203,"solution":833},{"grade":205,"solution":1937},{"grade":1020,"solution":692},{"grade":1142,"solution":154},{"grade":1245,"solution":1366}]},{"grade":1110,"move":363,"children":[{"grade":5100,"solution":363},{"grade":4060,"solution":1418}]},{"grade":1120,"solution":982},{"grade":1121,"move":1003,"children":[{"grade":5100,"solution":1003},{"grade":3237,"solution":1757}]},{"grade":1123,"solution":1512},{"grade":1132,"solution":1028},{"grade":1141,"move":1442,"children":[{"grade":5100,"solution":1442},{"grade":4080,"solution":2085}]},{"grade":1212,"solution":1822},{"grade":2030,"solution":2158},{"grade":2040,"move":939,"children":[{"grade":5100,"solution":939},{"grade":4060,"solution":1624}]},{"grade":2060,"solution":2167},{"grade":2144,"move":235,"children":[{"grade":5100,"solution":235},{"grade":4060,"solution":1987}]},{"grade":2151,"solution":950},{"grade":2246,"solution":1931},{"grade":3060,"solution":1066},{"grade":3070,"solution":111}]},{"move":1630,"grade":1010,"children":[{"move":12,"grade":0,"children":[{"grade":0,"solution":2094},{"grade":104,"solution":589},{"grade":1134,"solution":2175},{"grade":1236,"solution":1448},{"grade":2060,"solution":395}]},{"grade":100,"solution":266},{"grade":102,"solution":108},{"move":130,"grade":103,"children":[{"grade":0,"solution":8},{"grade":205,"solution":69},{"grade":1040,"solution":201},{"grade":1132,"solution":1099},{"grade":1140,"solution":1196},{"grade":1232,"solution":1229},{"grade":1233,"solution":2099}]},{"grade":104,"solution":863},{"grade":201,"solution":1213},{"move":90,"grade":203,"children":[{"grade":0,"solution":1739},{"grade":101,"solution":291},{"grade":102,"solution":1120},{"grade":1030,"solution":567},{"grade":1131,"solution":2254}]},{"grade":204,"solution":1947},{"move":12,"grade":205,"children":[{"grade":303,"solution":916},{"grade":1101,"solution":497},{"grade":3161,"solution":1268}]},{"grade":206,"solution":105},{"move":8,"grade":207,"children":[{"grade":2113,"solution":640},{"grade":3040,"solution":2263},{"grade":4080,"solution":2108}]},{"grade":305,"move":332,"children":[{"grade":5100,"solution":332},{"grade":4060,"solution":1843}]},{"grade":306,"move":1204,"children":[{"grade":5100,"solution":1204},{"grade":4080,"solution":1459}]},{"grade":406,"solution":1839},{"grade":1020,"move":258,"children":[{"grade":5100,"solution":258},{"grade":3134,"solution":2180}]},{"grade":1030,"solution":2112},{"grade":1040,"solution":297},{"grade":1120,"solution":1915},{"grade":1142,"solution":579},{"grade":1143,"move":101,"children":[{"grade":5100,"solution":101},{"grade":2255,"solution":943}]},{"grade":2020,"solution":1948},{"grade":2030,"move":362,"children":[{"grade":5100,"solution":362},{"grade":4060,"solution":1217}]},{"grade":2040,"solution":1259},{"grade":2050,"solution":1313},{"grade":2060,"solution":513},{"grade":2151,"solution":2115},{"move":12,"grade":2160,"children":[{"grade":101,"solution":1199},{"grade":203,"solution":392},{"grade":205,"solution":1935}]},{"grade":2161,"solution":2233},{"grade":2244,"solution":783},{"grade":2263,"solution":993},{"grade":3050,"solution":1462},{"grade":3060,"solution":1123},{"grade":3151,"solution":230}]},{"move":3320,"grade":1020,"children":[{"grade":0,"solution":2126},{"grade":102,"solution":1953},{"grade":204,"solution":117},{"grade":1030,"solution":481},{"grade":1112,"solution":1364},{"grade":1130,"solution":510},{"grade":1141,"solution":422},{"grade":1142,"solution":1208},{"grade":1212,"solution":1476},{"grade":1243,"solution":1454},{"grade":2040,"solution":1280},{"grade":2142,"solution":1752},{"grade":2152,"solution":853}]},{"move":11954,"grade":1030,"children":[{"move":22,"grade":0,"children":[{"grade":0,"solution":1881},{"grade":100,"solution":1450},{"grade":1010,"solution":834}]},{"grade":100,"solution":445},{"move":196,"grade":101,"children":[{"grade":103,"solution":1151},{"grade":203,"solution":923},{"grade":205,"solution":82},{"grade":1113,"solution":551},{"grade":1123,"solution":1236}]},{"grade":102,"solution":2053},{"move":1160,"grade":103,"children":[{"grade":0,"solution":1599},{"grade":100,"move":626,"children":[{"grade":5100,"solution":626},{"grade":2233,"solution":2000}]},{"grade":101,"solution":2052},{"grade":103,"solution":532},{"grade":104,"move":1107,"children":[{"grade":5100,"solution":1107},{"grade":3151,"solution":1410}]},{"grade":201,"solution":627},{"grade":307,"solution":1178},{"grade":1010,"move":1572,"children":[{"grade":5100,"solution":1572},{"grade":4060,"solution":2281}]},{"grade":1040,"solution":2},{"grade":1110,"solution":1571},{"grade":1113,"solution":1683},{"grade":1141,"solution":869},{"grade":2050,"solution":1015}]},{"move":32,"grade":104,"children":[{"grade":101,"solution":1629},{"grade":205,"solution":2089},{"grade":305,"solution":1514},{"grade":1010,"solution":682},{"grade":1112,"solution":1649},{"grade":1121,"solution":120},{"grade":1225,"solution":2016}]},{"grade":201,"solution":641},{"move":12,"grade":203,"children":[{"grade":102,"solution":1730},{"grade":202,"solution":1061},{"grade":306,"solution":1004},{"grade":1020,"solution":2083}]},{"move":10,"grade":204,"children":[{"grade":101,"solution":325},{"grade":1010,"solution":637},{"grade":2114,"solution":1859}]},{"grade":205,"solution":1731},{"move":2924,"grade":207,"children":[{"grade":101,"solution":148},{"grade":1010,"move":734,"children":[{"grade":5100,"solution":734},{"grade":4060,"solution":1598}]},{"grade":1110,"solution":1804},{"grade":2030,"solution":1734},{"grade":2050,"solution":1360}]},{"grade":307,"solution":1314},{"grade":308,"solution":359},{"move":8,"grade":1000,"children":[{"grade":100,"solution":1719},{"grade":1020,"solution":251},{"grade":1120,"solution":1970}]},{"grade":1010,"move":514,"children":[{"grade":5100,"solution":514},{"grade":3144,"solution":1563}]},{"grade":1020,"move":1762,"children":[{"grade":5100,"solution":1762},{"grade":3291,"solution":1787}]},{"grade":1101,"move":386,"children":[{"grade":5100,"solution":386},{"grade":4060,"solution":1533}]},{"grade":1110,"solution":1903},{"grade":1112,"move":938,"children":[{"grade":5100,"solution":938},{"grade":3040,"solution":1979}]},{"grade":1114,"solution":989},{"move":308,"grade":1123,"children":[{"grade":101,"solution":2037},{"grade":204,"solution":1089},{"grade":1010,"solution":1747},{"grade":1141,"solution":1898}]},{"grade":1124,"move":381,"children":[{"grade":5100,"solution":381},{"grade":3060,"solution":1264}]},{"grade":1141,"move":832,"children":[{"grade":5100,"solution":832},{"grade":4090,"solution":1492}]},{"grade":1143,"solution":331},{"grade":1203,"solution":1334},{"grade":1204,"solution":333},{"grade":1212,"solution":1619},{"grade":1223,"solution":1466},{"grade":1227,"solution":615},{"grade":1241,"solution":161},{"grade":2030,"move":51,"children":[{"grade":5100,"solution":51},{"grade":3160,"solution":1955}]},{"grade":2040,"solution":2155},{"grade":2133,"solution":517}]},{"move":8548,"grade":1040,"children":[{"move":262,"grade":100,"children":[{"grade":1121,"solution":947},{"grade":1225,"solution":2139},{"grade":2030,"solution":302},{"grade":2225,"solution":278}]},{"grade":103,"solution":1901},{"grade":201,"solution":1906},{"grade":204,"move":160,"children":[{"grade":5100,"solution":160},{"grade":3191,"solution":260}]},{"grade":306,"move":1574,"children":[{"grade":5100,"solution":1574},{"grade":4100,"solution":2071}]},{"grade":308,"solution":444},{"grade":1020,"move":728,"children":[{"grade":5100,"solution":728},{"grade":3090,"solution":1176}]},{"grade":1030,"solution":1275},{"grade":1103,"move":254,"children":[{"grade":5100,"solution":254},{"grade":4090,"solution":629}]},{"grade":1121,"move":46,"children":[{"grade":5100,"solution":46},{"grade":3191,"solution":2253}]},{"grade":1124,"solution":299},{"move":52,"grade":1130,"children":[{"grade":1010,"solution":1748},{"grade":2010,"solution":588},{"grade":3030,"solution":122}]},{"grade":1134,"move":1232,"children":[{"grade":5100,"solution":1232},{"grade":3191,"solution":2279}]},{"grade":1204,"move":1101,"children":[{"grade":5100,"solution":1101},{"grade":4090,"solution":2074}]},{"grade":1213,"solution":1890},{"grade":1221,"solution":1076},{"grade":1234,"solution":1930},{"grade":1235,"solution":25},{"grade":1308,"solution":2079},{"grade":2010,"solution":733},{"grade":2020,"solution":469},{"grade":2030,"solution":1047},{"grade":2040,"solution":419},{"grade":2050,"solution":657},{"grade":2154,"solution":565},{"grade":3050,"solution":2062},{"grade":3060,"solution":224}]},{"move":2334,"grade":1101,"children":[{"move":1958,"grade":104,"children":[{"grade":0,"move":207,"children":[{"grade":5100,"solution":207},{"grade":3040,"solution":952}]},{"grade":101,"solution":685},{"grade":102,"solution":349},{"grade":202,"solution":1170},{"grade":206,"solution":20}]},{"grade":204,"move":1810,"children":[{"grade":5100,"solution":1810},{"grade":3070,"solution":1850}]},{"grade":309,"solution":94},{"grade":1040,"move":631,"children":[{"grade":5100,"solution":631},{"grade":4080,"solution":1721}]},{"move":148,"grade":1114,"children":[{"move":1924,"grade":0,"children":[{"grade":102,"solution":1864},{"grade":202,"solution":1728},{"grade":206,"solution":1873},{"grade":1020,"solution":1851}]},{"grade":102,"move":700,"children":[{"grade":5100,"solution":700},{"grade":4080,"solution":2010}]},{"grade":206,"solution":981},{"grade":1020,"move":731,"children":[{"grade":5100,"solution":731},{"grade":4164,"solution":1645}]},{"grade":1040,"move":35,"children":[{"grade":5100,"solution":35},{"grade":4182,"solution":468}]},{"grade":1121,"solution":701},{"grade":1140,"solution":360}]},{"grade":1124,"solution":642},{"grade":1143,"solution":824},{"grade":1214,"move":573,"children":[{"grade":5100,"solution":573},{"grade":4080,"solution":1601}]},{"grade":1216,"move":837,"children":[{"grade":5100,"solution":837},{"grade":4080,"solution":867}]},{"grade":1217,"solution":528},{"grade":2050,"solution":1368},{"grade":2070,"solution":2064},{"grade":2134,"solution":779},{"grade":2152,"solution":1502},{"grade":2153,"solution":2027},{"grade":2237,"solution":1870}]},{"grade":1102,"solution":86},{"move":4522,"grade":1103,"children":[{"grade":0,"solution":1888},{"grade":103,"move":712,"children":[{"grade":5100,"solution":712},{"grade":4060,"solution":752}]},{"grade":203,"solution":1956},{"grade":204,"solution":275},{"grade":205,"solution":1168},{"grade":207,"solution":1182},{"grade":306,"solution":455},{"grade":1123,"solution":1002},{"grade":1143,"solution":1452}]},{"move":24,"grade":1104,"children":[{"grade":0,"solution":1376},{"grade":100,"solution":237},{"grade":203,"solution":2106},{"grade":1112,"solution":1508},{"grade":2161,"solution":336}]},{"move":3392,"grade":1110,"children":[{"grade":102,"solution":1059},{"move":814,"grade":203,"children":[{"grade":103,"solution":1885},{"grade":203,"solution":521},{"grade":205,"solution":437},{"grade":1030,"solution":43},{"grade":1103,"solution":1378},{"grade":1143,"solution":1035},{"grade":1205,"solution":992}]},{"grade":206,"solution":1054},{"grade":303,"move":884,"children":[{"grade":5100,"solution":884},{"grade":4100,"solution":1056}]},{"grade":307,"solution":807},{"move":104,"grade":1020,"children":[{"grade":3030,"solution":1114},{"grade":3070,"solution":1060},{"grade":3173,"solution":1136},{"grade":4070,"solution":593},{"grade":5100,"solution":104}]},{"grade":1203,"solution":1340},{"grade":1243,"move":172,"children":[{"grade":5100,"solution":172},{"grade":4100,"solution":1021}]},{"grade":1245,"solution":1703},{"grade":2020,"move":1724,"children":[{"grade":5100,"solution":1724},{"grade":4060,"solution":2307}]},{"grade":2050,"solution":293},{"grade":2121,"solution":2276},{"grade":2132,"solution":298},{"grade":3050,"solution":1751},{"grade":3090,"solution":718}]},{"move":12,"grade":1112,"children":[{"grade":201,"solution":428},{"grade":203,"solution":371},{"grade":305,"solution":2004},{"grade":1132,"solution":1082}]},{"move":12,"grade":1113,"children":[{"grade":0,"solution":1964},{"grade":100,"solution":727},{"grade":1000,"solution":1936},{"grade":1203,"solution":918}]},{"move":596,"grade":1114,"children":[{"grade":0,"move":808,"children":[{"grade":5100,"solution":808},{"grade":1319,"solution":1006}]},{"grade":103,"solution":864},{"grade":104,"solution":890},{"grade":205,"solution":442},{"grade":206,"solution":6},{"grade":308,"solution":466},{"grade":1030,"solution":2076},{"grade":1040,"solution":1095},{"grade":1134,"solution":1438},{"grade":1236,"solution":1038},{"grade":2030,"solution":750}]},{"grade":1120,"move":145,"children":[{"grade":5100,"solution":145},{"grade":2161,"solution":1256}]},{"move":1504,"grade":1121,"children":[{"grade":0,"solution":2173},{"grade":102,"solution":1252},{"grade":104,"solution":1119},{"grade":207,"solution":964},{"grade":303,"solution":1701},{"grade":305,"solution":1838},{"grade":1000,"solution":1900},{"grade":1030,"solution":1441},{"grade":2010,"solution":664},{"grade":2114,"solution":643}]},{"move":6,"grade":1123,"children":[{"grade":0,"solution":1642},{"grade":103,"solution":1622},{"grade":1130,"solution":2296}]},{"move":2134,"grade":1130,"children":[{"grade":100,"solution":2246},{"grade":103,"move":1773,"children":[{"grade":5100,"solution":1773},{"grade":4060,"solution":2070}]},{"grade":104,"solution":2095},{"grade":202,"solution":1353},{"grade":203,"solution":574},{"grade":204,"solution":601},{"grade":205,"solution":2031},{"grade":206,"solution":710},{"grade":207,"solution":56},{"grade":1104,"solution":2048},{"grade":1140,"solution":666},{"grade":2010,"solution":564}]},{"move":6824,"grade":1131,"children":[{"grade":0,"solution":1231},{"grade":101,"solution":462},{"grade":103,"solution":1159},{"grade":104,"solution":644},{"grade":202,"solution":1652},{"grade":205,"solution":1058},{"grade":1020,"solution":1032},{"grade":1110,"solution":883}]},{"move":3102,"grade":1132,"children":[{"grade":100,"solution":1375},{"grade":103,"solution":476},{"grade":203,"solution":199},{"grade":204,"solution":409},{"grade":205,"solution":599},{"grade":1010,"solution":1973},{"grade":1020,"solution":1312},{"grade":1121,"move":1017,"children":[{"grade":5100,"solution":1017},{"grade":4100,"solution":1817}]},{"grade":1123,"solution":341},{"grade":1143,"solution":917},{"grade":1223,"solution":622},{"grade":2060,"solution":1409},{"grade":2163,"solution":1852}]},{"move":9018,"grade":1134,"children":[{"grade":0,"solution":48},{"grade":100,"solution":1070},{"move":116,"grade":101,"children":[{"grade":0,"solution":1131},{"grade":102,"solution":2162},{"grade":1040,"solution":1793}]},{"grade":103,"solution":1788},{"grade":205,"move":633,"children":[{"grade":5100,"solution":633},{"grade":3273,"solution":1940}]},{"grade":207,"solution":1821},{"grade":1000,"solution":2219},{"grade":1020,"move":714,"children":[{"grade":5100,"solution":714},{"grade":4060,"solution":1097}]},{"grade":1040,"solution":189},{"grade":1123,"move":217,"children":[{"grade":5100,"solution":217},{"grade":4060,"solution":300}]},{"grade":1141,"solution":968},{"grade":1143,"solution":2257},{"grade":1223,"solution":895},{"grade":2060,"solution":2242}]},{"move":288,"grade":1140,"children":[{"move":8,"grade":103,"children":[{"grade":0,"solution":2101},{"grade":100,"solution":1315},{"grade":102,"solution":2046},{"grade":104,"solution":1594}]},{"grade":203,"solution":1676},{"grade":205,"solution":98},{"grade":309,"solution":1834},{"grade":1030,"move":1478,"children":[{"grade":5100,"solution":1478},{"grade":3090,"solution":2007}]},{"grade":1103,"move":1709,"children":[{"grade":5100,"solution":1709},{"grade":4090,"solution":2160}]},{"grade":1123,"solution":820},{"move":12,"grade":1130,"children":[{"grade":101,"solution":730},{"grade":1010,"solution":662},{"grade":1112,"solution":904},{"grade":2010,"solution":1461}]},{"grade":1131,"solution":961},{"grade":1134,"solution":23},{"grade":1231,"solution":1077},{"grade":1232,"solution":1191},{"grade":1234,"solution":1122},{"grade":2030,"move":1365,"children":[{"grade":5100,"solution":1365},{"grade":3172,"solution":1684}]},{"move":1048,"grade":2050,"children":[{"grade":1121,"solution":686},{"grade":1221,"solution":2153},{"grade":1224,"solution":823},{"grade":1225,"solution":1026},{"grade":2030,"solution":754},{"grade":2224,"solution":1053}]},{"grade":2123,"solution":1214},{"grade":2144,"solution":1322},{"grade":2151,"solution":746},{"grade":2244,"solution":346},{"grade":3040,"solution":1611},{"grade":3050,"solution":2237}]},{"move":10514,"grade":1141,"children":[{"move":1146,"grade":0,"children":[{"grade":102,"solution":2145},{"grade":206,"solution":776},{"grade":307,"solution":819},{"grade":1020,"solution":1811},{"grade":1102,"solution":242},{"grade":1112,"solution":326},{"grade":2020,"solution":1779},{"grade":3030,"solution":2021}]},{"grade":100,"solution":1835},{"grade":101,"solution":1706},{"move":6,"grade":102,"children":[{"grade":306,"solution":1193},{"grade":1233,"solution":292},{"grade":2151,"solution":1549}]},{"grade":104,"move":459,"children":[{"grade":5100,"solution":459},{"grade":4200,"solution":919}]},{"grade":201,"solution":1847},{"grade":202,"solution":1666},{"grade":204,"solution":500},{"grade":205,"solution":620},{"grade":207,"solution":1623},{"grade":307,"solution":140},{"grade":1000,"solution":1920},{"grade":1010,"solution":2295},{"move":6,"grade":1030,"children":[{"grade":203,"solution":182},{"grade":303,"solution":1456},{"grade":307,"solution":690}]},{"grade":1102,"solution":586},{"grade":1103,"solution":1331},{"grade":1104,"move":1282,"children":[{"grade":5100,"solution":1282},{"grade":3153,"solution":1771}]},{"grade":1131,"solution":253},{"grade":1134,"solution":1718},{"grade":1236,"solution":587},{"grade":2030,"solution":1330},{"grade":2114,"solution":1078},{"grade":2134,"solution":646}]},{"grade":1142,"move":744,"children":[{"grade":5100,"solution":744},{"grade":2160,"solution":941}]},{"move":12,"grade":1143,"children":[{"move":14,"grade":0,"children":[{"grade":102,"solution":1661},{"grade":203,"solution":240},{"grade":2020,"solution":1523}]},{"move":46,"grade":100,"children":[{"grade":1244,"solution":1578},{"grade":2171,"solution":794},{"grade":3171,"solution":747},{"grade":4080,"solution":134}]},{"grade":101,"solution":841},{"grade":104,"solution":1323},{"grade":202,"solution":983},{"grade":203,"solution":1758},{"grade":204,"solution":1673},{"grade":205,"solution":2152},{"grade":1000,"solution":150},{"grade":1010,"solution":449},{"grade":1030,"solution":175},{"grade":1134,"solution":1075}]},{"move":130,"grade":1203,"children":[{"grade":0,"solution":338},{"grade":100,"solution":1981},{"grade":101,"solution":1503}]},{"move":8,"grade":1204,"children":[{"grade":204,"solution":295},{"grade":304,"solution":304},{"grade":1131,"solution":193},{"grade":2171,"solution":1273}]},{"grade":1205,"move":1288,"children":[{"grade":5100,"solution":1288},{"grade":1309,"solution":1668}]},{"grade":1207,"solution":566},{"grade":1212,"move":136,"children":[{"grade":5100,"solution":136},{"grade":3080,"solution":602}]},{"grade":1213,"move":171,"children":[{"grade":5100,"solution":171},{"grade":4100,"solution":1430}]},{"move":12,"grade":1214,"children":[{"grade":0,"solution":339},{"grade":101,"solution":474},{"grade":104,"solution":2271}]},{"grade":1217,"solution":1200},{"grade":1221,"move":73,"children":[{"grade":5100,"solution":73},{"grade":2163,"solution":404}]},{"grade":1227,"solution":1335},{"grade":1231,"move":345,"children":[{"grade":5100,"solution":345},{"grade":3160,"solution":1144}]},{"move":12,"grade":1232,"children":[{"grade":0,"solution":358},{"grade":100,"solution":2059},{"grade":203,"solution":1317},{"grade":1121,"solution":757}]},{"grade":1233,"solution":1736},{"grade":1234,"move":707,"children":[{"grade":5100,"solution":707},{"grade":1233,"solution":1269}]},{"move":490,"grade":1241,"children":[{"move":1244,"grade":0,"children":[{"grade":102,"solution":512},{"grade":1020,"move":41,"children":[{"grade":5100,"solution":41},{"grade":3090,"solution":417}]},{"grade":1124,"solution":2159},{"grade":1227,"solution":203},{"grade":2020,"solution":186},{"grade":2112,"solution":605},{"grade":2123,"solution":1723},{"grade":3030,"solution":544}]},{"grade":100,"move":453,"children":[{"grade":5100,"solution":453},{"grade":4100,"solution":1705}]},{"grade":101,"solution":1786},{"grade":102,"solution":1829},{"grade":103,"solution":1658},{"grade":104,"solution":67},{"grade":201,"solution":1803},{"grade":205,"solution":1385},{"grade":1010,"solution":45},{"grade":1104,"solution":1062}]},{"move":948,"grade":1243,"children":[{"grade":0,"solution":2183},{"grade":205,"solution":1581},{"grade":1227,"solution":2207},{"grade":2050,"solution":936},{"grade":2150,"solution":2151},{"grade":2154,"solution":1694},{"grade":3164,"solution":218},{"grade":4060,"solution":1894}]},{"move":210,"grade":1244,"children":[{"grade":406,"solution":756},{"grade":1213,"solution":548},{"grade":1231,"solution":1636},{"grade":1315,"solution":2107},{"grade":2140,"solution":959},{"grade":2242,"solution":973}]},{"grade":1245,"solution":427},{"grade":1328,"solution":795},{"grade":1343,"solution":306},{"grade":1344,"solution":1680},{"move":4506,"grade":2010,"children":[{"grade":0,"solution":1860},{"grade":102,"move":137,"children":[{"grade":5100,"solution":137},{"grade":2217,"solution":713}]},{"grade":103,"move":424,"children":[{"grade":5100,"solution":424},{"grade":4070,"solution":960}]},{"grade":104,"solution":1190},{"grade":203,"solution":1029},{"grade":204,"solution":2150},{"grade":1020,"move":211,"children":[{"grade":5100,"solution":211},{"grade":4060,"solution":790}]},{"grade":1030,"solution":781},{"grade":1121,"solution":1564},{"grade":2070,"solution":1677}]},{"grade":2020,"solution":2298},{"move":7388,"grade":2030,"children":[{"grade":0,"solution":2224},{"move":2412,"grade":103,"children":[{"move":8954,"grade":1010,"children":[{"grade":1010,"solution":771},{"grade":1110,"solution":2291},{"grade":1114,"solution":1547},{"grade":2030,"solution":143},{"grade":2050,"solution":1519}]},{"grade":1110,"solution":2222},{"grade":1112,"solution":1749},{"grade":1113,"solution":2191},{"grade":1213,"solution":1327},{"grade":2030,"solution":848},{"grade":2133,"solution":899}]},{"grade":202,"solution":985},{"grade":203,"move":153,"children":[{"grade":5100,"solution":153},{"grade":4060,"solution":652}]},{"grade":205,"solution":2069},{"grade":207,"solution":2110},{"grade":305,"solution":1716},{"grade":1123,"solution":1195},{"grade":1143,"solution":398},{"grade":1217,"solution":1041},{"grade":1243,"solution":1580},{"grade":2010,"solution":580},{"grade":2040,"solution":1186},{"grade":3040,"move":1741,"children":[{"grade":5100,"solution":1741},{"grade":4060,"solution":2138}]},{"grade":3080,"solution":1738}]},{"move":132,"grade":2040,"children":[{"grade":0,"solution":1789},{"grade":101,"move":178,"children":[{"grade":5100,"solution":178},{"grade":3040,"solution":612}]},{"grade":102,"move":1124,"children":[{"grade":5100,"solution":1124},{"grade":3050,"solution":1700}]},{"grade":201,"solution":1463},{"grade":1132,"solution":885},{"grade":1233,"solution":1780},{"grade":1236,"solution":1950},{"grade":2050,"solution":2030}]},{"move":2254,"grade":2050,"children":[{"grade":0,"solution":1034},{"move":22,"grade":104,"children":[{"grade":0,"solution":44},{"grade":100,"move":680,"children":[{"grade":5100,"solution":680},{"grade":4060,"solution":1434}]},{"grade":201,"solution":1800},{"grade":202,"solution":893},{"grade":1140,"solution":1902}]},{"grade":204,"solution":226},{"grade":206,"solution":396},{"grade":207,"solution":2255},{"grade":1000,"solution":741},{"grade":1010,"solution":1336},{"grade":1040,"solution":2067},{"grade":1113,"solution":368},{"grade":1114,"solution":166},{"grade":1212,"solution":755},{"grade":1213,"solution":1586},{"grade":1214,"solution":1567},{"grade":2010,"solution":2072},{"grade":3030,"solution":1525}]},{"move":8,"grade":2070,"children":[{"grade":104,"solution":412},{"grade":1020,"solution":96},{"grade":2020,"solution":882}]},{"grade":2113,"move":135,"children":[{"grade":5100,"solution":135},{"grade":4060,"solution":1022}]},{"move":372,"grade":2121,"children":[{"grade":104,"solution":1772},{"grade":204,"solution":1426},{"grade":207,"solution":1257},{"grade":1040,"solution":2184},{"grade":2050,"solution":400}]},{"grade":2130,"move":994,"children":[{"grade":5100,"solution":994},{"grade":2134,"solution":2275}]},{"grade":2131,"solution":846},{"grade":2132,"solution":1305},{"grade":2134,"solution":719},{"grade":2140,"move":174,"children":[{"grade":5100,"solution":174},{"grade":3246,"solution":2299}]},{"grade":2141,"move":270,"children":[{"grade":5100,"solution":270},{"grade":4080,"solution":1220}]},{"grade":2143,"move":912,"children":[{"grade":5100,"solution":912},{"grade":2141,"solution":1446}]},{"grade":2144,"solution":384},{"move":122,"grade":2150,"children":[{"grade":0,"solution":1338},{"grade":1000,"solution":2020},{"grade":1141,"solution":350},{"grade":1143,"solution":33},{"grade":1243,"solution":639},{"grade":2040,"solution":2029},{"grade":2070,"solution":1164}]},{"grade":2151,"solution":809},{"grade":2161,"solution":2047},{"grade":2244,"solution":1391},{"grade":2271,"solution":1997},{"grade":3030,"solution":220},{"move":28,"grade":3050,"children":[{"grade":104,"solution":492},{"grade":307,"solution":200},{"grade":410,"solution":1357},{"grade":1040,"solution":763},{"grade":1337,"solution":1316}]},{"grade":3070,"solution":1361},{"grade":3144,"solution":1791},{"grade":5100,"solution":0}]}